Workbook
Name Slicer_Category: #N/A
Name Slicer_Region: #N/A
Name Slicer_Salesperson: #N/A

Sheet Dashboard
H26: =GETPIVOTDATA("Total Sales",'Pivot Data'!$A$3) -> 4072350.1 | I26: =GETPIVOTDATA("Total Profit",'Pivot Data'!$A$3) -> 655542.86 | J26: =GETPIVOTDATA("Total Orders",'Pivot Data'!$A$3) -> 1500
T28: =ROUND(H26,0) -> 4072350
S33: =GETPIVOTDATA("Total Sales",'Pivot Data'!$A$3) -> 4072350.1 | T33: =GETPIVOTDATA("Total Orders",'Pivot Data'!$A$3) -> 1500
S34: =GETPIVOTDATA("Total Profit",'Pivot Data'!$A$3) -> 655542.86
C37: #VALUE!
S39: ='Pivot Data'!D4 -> 0.16097409

Sheet Raw data
A1: Date | B1: Region | C1: Product | D1: Column1 | E1: Column2 | F1: Category | G1: Quantity | H1: UnitPrice | I1: StoreLocation | J1: CustomerType | K1: Discount | L1: Salesperson | M1: TotalPrice | N1: PaymentMethod | O1: Promotion | P1: Returned | Q1: OrderID | R1: CustomerName | S1: ShippingCost | T1: OrderDate | U1: DeliveryDate | V1: RegionManager | W1: Net Sales | X1: Sales | Y1: Profit | Z1: Discount Category | AA1: Year-Month
A2: 44980 | B2: East | C2: Laptop | D2: =TRIM(Table1[[#This Row],[Product]]) -> Laptop | E2: =PROPER(Table1[[#This Row],[Column1]]) -> Laptop | F2: =IF(OR(E2="Chair",E2="Desk"),"Furniture",IF(OR(E2="Laptop",E2="Monitor",E2="Phone",E2="Tablet"),"Technology",IF(E2="Printer","Office Supplies","Other"))) -> Technology | G2: 14 | H2: 163.6 | I2: Store B | J2: Wholesale | K2: 0 | L2: Eva | M2: 2290.4 | N2: Online | O2: FREESHIP | P2: 0 | Q2: REG100000 | R2: Cust 6583 | S2: 43.34 | T2: 44980 | U2: 44984 | V2: Eric | W2: =M2*(1-K2) -> 2290.4 | X2: =G2*H2 -> 2290.4 | Y2: =X2-W2 -> 0 | Z2: =IF(K2=0,"No Discount",IF(K2<5%,"Low",IF(K2<15%,"Medium","High"))) -> No Discount | AA2: =DATE(YEAR(Table1[[#This Row],[OrderDate]]),MONTH(Table1[[#This Row],[OrderDate]]),1) -> 44958
A3: 45645 | B3: South | C3: Phone | D3: =TRIM(Table1[[#This Row],[Product]]) -> Phone | E3: =PROPER(Table1[[#This Row],[Column1]]) -> Phone | F3: =IF(OR(E3="Chair",E3="Desk"),"Furniture",IF(OR(E3="Laptop",E3="Monitor",E3="Phone",E3="Tablet"),"Technology",IF(E3="Printer","Office Supplies","Other"))) -> Technology | G3: 1 | H3: 544.01 | I3: Store A | J3: Retail | K3: 0 | L3: Alice | M3: 544.01 | N3: Gift Card | O3: SAVE10 | P3: 0 | Q3: REG100001 | R3: Cust 2144 | S3: 5.3 | T3: 45645 | U3: 45654 | V3: Sophie | W3: =M3*(1-K3) -> 544.01 | X3: =G3*H3 -> 544.01 | Y3: =X3-W3 -> 0 | AA3: =DATE(YEAR(Table1[[#This Row],[OrderDate]]),MONTH(Table1[[#This Row],[OrderDate]]),1) -> 45627
A4: 45056 | B4: North | C4: Desk | D4: =TRIM(Table1[[#This Row],[Product]]) -> Desk | E4: =PROPER(Table1[[#This Row],[Column1]]) -> Desk | F4: =IF(OR(E4="Chair",E4="Desk"),"Furniture",IF(OR(E4="Laptop",E4="Monitor",E4="Phone",E4="Tablet"),"Technology",IF(E4="Printer","Office Supplies","Other"))) -> Furniture | G4: 14 | H4: 346.18 | I4: Store B | J4: Wholesale | K4: 0.1 | L4: Alice | M4: 4361.868 | N4: Online | O4: WINTER15 | P4: 0 | Q4: REG100002 | R4: Cust 5998 | S4: 20.46 | T4: 45056 | U4: 45065 | V4: Ryan | W4: =M4*(1-K4) -> 3925.6812 | X4: =G4*H4 -> 4846.52 | Y4: =X4-W4 -> 920.8388 | Z4: =IF(K4=0,"No Discount",IF(K4<5%,"Low",IF(K4<15%,"Medium","High"))) -> Medium | AA4: =DATE(YEAR(Table1[[#This Row],[OrderDate]]),MONTH(Table1[[#This Row],[OrderDate]]),1) -> 45047
A5: 45714 | B5: Central | C5: Chair | D5: =TRIM(Table1[[#This Row],[Product]]) -> Chair | E5: =PROPER(Table1[[#This Row],[Column1]]) -> Chair | F5: =IF(OR(E5="Chair",E5="Desk"),"Furniture",IF(OR(E5="Laptop",E5="Monitor",E5="Phone",E5="Tablet"),"Technology",IF(E5="Printer","Office Supplies","Other"))) -> Furniture | G5: 18 | H5: 384.82 | I5: Store A | J5: Wholesale | K5: 0.15 | L5: Frank | M5: 5887.746 | N5: Gift Card | O5: FREESHIP | P5: 0 | Q5: REG100003 | R5: Cust 7136 | S5: 27.95 | T5: 45714 | U5: 45718 | V5: Cameron | W5: =M5*(1-K5) -> 5004.5841 | X5: =G5*H5 -> 6926.76 | Y5: =X5-W5 -> 1922.1759 | Z5: =IF(K5=0,"No Discount",IF(K5<5%,"Low",IF(K5<15%,"Medium","High"))) -> High | AA5: =DATE(YEAR(Table1[[#This Row],[OrderDate]]),MONTH(Table1[[#This Row],[OrderDate]]),1) -> 45689
A6: 45101 | B6: East | C6: Desk | D6: =TRIM(Table1[[#This Row],[Product]]) -> Desk | E6: =PROPER(Table1[[#This Row],[Column1]]) -> Desk | F6: =IF(OR(E6="Chair",E6="Desk"),"Furniture",IF(OR(E6="Laptop",E6="Monitor",E6="Phone",E6="Tablet"),"Technology",IF(E6="Printer","Office Supplies","Other"))) -> Furniture | G6: 18 | H6: 237.76 | I6: Store C | J6: Retail | K6: 0 | L6: Carlos | M6: 4279.68 | N6: Online | O6: SAVE10 | P6: 0 | Q6: REG100004 | R6: Cust 6506 | S6: 5.73 | T6: 45101 | U6: 45104 | V6: Eric | W6: =M6*(1-K6) -> 4279.68 | X6: =G6*H6 -> 4279.68 | Y6: =X6-W6 -> 0 | Z6: =IF(K6=0,"No Discount",IF(K6<5%,"Low",IF(K6<15%,"Medium","High"))) -> No Discount | AA6: =DATE(YEAR(Table1[[#This Row],[OrderDate]]),MONTH(Table1[[#This Row],[OrderDate]]),1) -> 45078
A7: 45342 | B7: Central | C7: Monitor | D7: =TRIM(Table1[[#This Row],[Product]]) -> Monitor | E7: =PROPER(Table1[[#This Row],[Column1]]) -> Monitor | F7: =IF(OR(E7="Chair",E7="Desk"),"Furniture",IF(OR(E7="Laptop",E7="Monitor",E7="Phone",E7="Tablet"),"Technology",IF(E7="Printer","Office Supplies","Other"))) -> Technology | G7: 2 | H7: 385.09 | I7: Store D | J7: Wholesale | K7: 0.15 | L7: Diana | M7: 654.653 | N7: Credit Card | P7: 0 | Q7: REG100005 | R7: Cust 3909 | S7: 11.92 | T7: 45342 | U7: 45352 | V7: Cameron | W7: =M7*(1-K7) -> 556.45505 | X7: =G7*H7 -> 770.18 | Y7: =X7-W7 -> 213.72495 | Z7: =IF(K7=0,"No Discount",IF(K7<5%,"Low",IF(K7<15%,"Medium","High"))) -> High | AA7: =DATE(YEAR(Table1[[#This Row],[OrderDate]]),MONTH(Table1[[#This Row],[OrderDate]]),1) -> 45323
A8: 44937 | B8: South | C8: Chair | D8: =TRIM(Table1[[#This Row],[Product]]) -> Chair | E8: =PROPER(Table1[[#This Row],[Column1]]) -> Chair | F8: =IF(OR(E8="Chair",E8="Desk"),"Furniture",IF(OR(E8="Laptop",E8="Monitor",E8="Phone",E8="Tablet"),"Technology",IF(E8="Printer","Office Supplies","Other"))) -> Furniture | G8: 7 | H8: 17.5 | I8: Store C | J8: Retail | K8: 0.1 | L8: Alice | M8: 110.25 | N8: Debit Card | O8: WINTER15 | P8: 0 | Q8: REG100006 | R8: Cust 7887 | S8: 5.02 | T8: 44937 | U8: 44940 | V8: Sophie | W8: =M8*(1-K8) -> 99.225 | X8: =G8*H8 -> 122.5 | Y8: =X8-W8 -> 23.275 | Z8: =IF(K8=0,"No Discount",IF(K8<5%,"Low",IF(K8<15%,"Medium","High"))) -> Medium | AA8: =DATE(YEAR(Table1[[#This Row],[OrderDate]]),MONTH(Table1[[#This Row],[OrderDate]]),1) -> 44927
A9: 44935 | B9: Central | C9: Chair | D9: =TRIM(Table1[[#This Row],[Product]]) -> Chair | E9: =PROPER(Table1[[#This Row],[Column1]]) -> Chair | F9: =IF(OR(E9="Chair",E9="Desk"),"Furniture",IF(OR(E9="Laptop",E9="Monitor",E9="Phone",E9="Tablet"),"Technology",IF(E9="Printer","Office Supplies","Other"))) -> Furniture | G9: 3 | H9: 330.22 | I9: Store C | J9: Wholesale | K9: 0.15 | L9: Carlos | M9: 842.061 | N9: Cash | P9: 0 | Q9: REG100007 | R9: Cust 5301 | S9: 48.01 | T9: 44935 | U9: 44937 | V9: Cameron | W9: =M9*(1-K9) -> 715.75185 | X9: =G9*H9 -> 990.66 | Y9: =X9-W9 -> 274.90815 | Z9: =IF(K9=0,"No Discount",IF(K9<5%,"Low",IF(K9<15%,"Medium","High"))) -> High | AA9: =DATE(YEAR(Table1[[#This Row],[OrderDate]]),MONTH(Table1[[#This Row],[OrderDate]]),1) -> 44927
A10: 45581 | B10: South | C10: Chair | D10: =TRIM(Table1[[#This Row],[Product]]) -> Chair | E10: =PROPER(Table1[[#This Row],[Column1]]) -> Chair | F10: =IF(OR(E10="Chair",E10="Desk"),"Furniture",IF(OR(E10="Laptop",E10="Monitor",E10="Phone",E10="Tablet"),"Technology",IF(E10="Printer","Office Supplies","Other"))) -> Furniture | G10: 3 | H10: 432.04 | I10: Store D | J10: Wholesale | K10: 0.05 | L10: Bob | M10: 1231.314 | N10: Debit Card | O10: FREESHIP | P10: 1 | Q10: REG100008 | R10: Cust 2284 | S10: 42.11 | T10: 45581 | U10: 45583 | V10: Sophie | W10: =M10*(1-K10) -> 1169.7483 | X10: =G10*H10 -> 1296.12 | Y10: =X10-W10 -> 126.3717 | Z10: =IF(K10=0,"No Discount",IF(K10<5%,"Low",IF(K10<15%,"Medium","High"))) -> Medium | AA10: =DATE(YEAR(Table1[[#This Row],[OrderDate]]),MONTH(Table1[[#This Row],[OrderDate]]),1) -> 45566
A11: 45721 | B11: West | C11: Desk | D11: =TRIM(Table1[[#This Row],[Product]]) -> Desk | E11: =PROPER(Table1[[#This Row],[Column1]]) -> Desk | F11: =IF(OR(E11="Chair",E11="Desk"),"Furniture",IF(OR(E11="Laptop",E11="Monitor",E11="Phone",E11="Tablet"),"Technology",IF(E11="Printer","Office Supplies","Other"))) -> Furniture | G11: 5 | H11: 323.28 | I11: Store D | J11: Retail | K11: 0.1 | L11: Frank | M11: 1454.76 | N11: Gift Card | O11: SAVE10 | P11: 0 | Q11: REG100009 | R11: Cust 3732 | S11: 41.1 | T11: 45721 | U11: 45729 | V11: Wendy | W11: =M11*(1-K11) -> 1309.284 | X11: =G11*H11 -> 1616.4 | Y11: =X11-W11 -> 307.116 | Z11: =IF(K11=0,"No Discount",IF(K11<5%,"Low",IF(K11<15%,"Medium","High"))) -> Medium | AA11: =DATE(YEAR(Table1[[#This Row],[OrderDate]]),MONTH(Table1[[#This Row],[OrderDate]]),1) -> 45717
A12: 45392 | B12: North | C12: Desk | D12: =TRIM(Table1[[#This Row],[Product]]) -> Desk | E12: =PROPER(Table1[[#This Row],[Column1]]) -> Desk | F12: =IF(OR(E12="Chair",E12="Desk"),"Furniture",IF(OR(E12="Laptop",E12="Monitor",E12="Phone",E12="Tablet"),"Technology",IF(E12="Printer","Office Supplies","Other"))) -> Furniture | G12: 15 | H12: 523.29 | I12: Store B | J12: Wholesale | K12: 0.15 | L12: Eva | M12: 6671.9475 | N12: Debit Card | P12: 0 | Q12: REG100010 | R12: Cust 1462 | S12: 12.14 | T12: 45392 | U12: 45399 | V12: Ryan | W12: =M12*(1-K12) -> 5671.1554 | X12: =G12*H12 -> 7849.35 | Y12: =X12-W12 -> 2178.1946 | Z12: =IF(K12=0,"No Discount",IF(K12<5%,"Low",IF(K12<15%,"Medium","High"))) -> High | AA12: =DATE(YEAR(Table1[[#This Row],[OrderDate]]),MONTH(Table1[[#This Row],[OrderDate]]),1) -> 45383
A13: 45485 | B13: East | C13: Phone | D13: =TRIM(Table1[[#This Row],[Product]]) -> Phone | E13: =PROPER(Table1[[#This Row],[Column1]]) -> Phone | F13: =IF(OR(E13="Chair",E13="Desk"),"Furniture",IF(OR(E13="Laptop",E13="Monitor",E13="Phone",E13="Tablet"),"Technology",IF(E13="Printer","Office Supplies","Other"))) -> Technology | G13: 19 | H13: 207.35 | I13: Store D | J13: Retail | K13: 0.1 | L13: Eva | M13: 3545.685 | N13: Gift Card | P13: 1 | Q13: REG100011 | R13: Cust 4330 | S13: 44.89 | T13: 45485 | U13: 45491 | V13: Eric | W13: =M13*(1-K13) -> 3191.1165 | X13: =G13*H13 -> 3939.65 | Y13: =X13-W13 -> 748.5335 | Z13: =IF(K13=0,"No Discount",IF(K13<5%,"Low",IF(K13<15%,"Medium","High"))) -> Medium | AA13: =DATE(YEAR(Table1[[#This Row],[OrderDate]]),MONTH(Table1[[#This Row],[OrderDate]]),1) -> 45474
A14: 45128 | B14: Central | C14: Phone | D14: =TRIM(Table1[[#This Row],[Product]]) -> Phone | E14: =PROPER(Table1[[#This Row],[Column1]]) -> Phone | F14: =IF(OR(E14="Chair",E14="Desk"),"Furniture",IF(OR(E14="Laptop",E14="Monitor",E14="Phone",E14="Tablet"),"Technology",IF(E14="Printer","Office Supplies","Other"))) -> Technology | G14: 1 | H14: 120.53 | I14: Store B | J14: Retail | K14: 0.05 | L14: Diana | M14: 114.5035 | N14: Cash | O14: WINTER15 | P14: 0 | Q14: REG100012 | R14: Cust 2372 | S14: 20.35 | T14: 45128 | U14: 45138 | V14: Cameron | W14: =M14*(1-K14) -> 108.77832 | X14: =G14*H14 -> 120.53 | Y14: =X14-W14 -> 11.751675 | Z14: =IF(K14=0,"No Discount",IF(K14<5%,"Low",IF(K14<15%,"Medium","High"))) -> Medium | AA14: =DATE(YEAR(Table1[[#This Row],[OrderDate]]),MONTH(Table1[[#This Row],[OrderDate]]),1) -> 45108
A15: 45675 | B15: West | C15: Tablet | D15: =TRIM(Table1[[#This Row],[Product]]) -> Tablet | E15: =PROPER(Table1[[#This Row],[Column1]]) -> Tablet | F15: =IF(OR(E15="Chair",E15="Desk"),"Furniture",IF(OR(E15="Laptop",E15="Monitor",E15="Phone",E15="Tablet"),"Technology",IF(E15="Printer","Office Supplies","Other"))) -> Technology | G15: 1 | H15: 157.83 | I15: Store A | J15: Wholesale | K15: 0.15 | L15: Carlos | M15: 134.1555 | N15: Debit Card | P15: 0 | Q15: REG100013 | R15: Cust 4672 | S15: 42.82 | T15: 45675 | U15: 45679 | V15: Wendy | W15: =M15*(1-K15) -> 114.03217 | X15: =G15*H15 -> 157.83 | Y15: =X15-W15 -> 43.797825 | Z15: =IF(K15=0,"No Discount",IF(K15<5%,"Low",IF(K15<15%,"Medium","High"))) -> High | AA15: =DATE(YEAR(Table1[[#This Row],[OrderDate]]),MONTH(Table1[[#This Row],[OrderDate]]),1) -> 45658
A16: 45634 | B16: North | C16: Desk | D16: =TRIM(Table1[[#This Row],[Product]]) -> Desk | E16: =PROPER(Table1[[#This Row],[Column1]]) -> Desk | F16: =IF(OR(E16="Chair",E16="Desk"),"Furniture",IF(OR(E16="Laptop",E16="Monitor",E16="Phone",E16="Tablet"),"Technology",IF(E16="Printer","Office Supplies","Other"))) -> Furniture | G16: 15 | H16: 220.3 | I16: Store B | J16: Retail | K16: 0.15 | L16: Diana | M16: 2808.825 | N16: Debit Card | P16: 0 | Q16: REG100014 | R16: Cust 4548 | S16: 39.66 | T16: 45634 | U16: 45641 | V16: Ryan | W16: =M16*(1-K16) -> 2387.5012 | X16: =G16*H16 -> 3304.5 | Y16: =X16-W16 -> 916.99875 | Z16: =IF(K16=0,"No Discount",IF(K16<5%,"Low",IF(K16<15%,"Medium","High"))) -> High | AA16: =DATE(YEAR(Table1[[#This Row],[OrderDate]]),MONTH(Table1[[#This Row],[OrderDate]]),1) -> 45627
A17: 45788 | B17: West | C17: Chair | D17: =TRIM(Table1[[#This Row],[Product]]) -> Chair | E17: =PROPER(Table1[[#This Row],[Column1]]) -> Chair | F17: =IF(OR(E17="Chair",E17="Desk"),"Furniture",IF(OR(E17="Laptop",E17="Monitor",E17="Phone",E17="Tablet"),"Technology",IF(E17="Printer","Office Supplies","Other"))) -> Furniture | G17: 17 | H17: 162.96 | I17: Store A | J17: Wholesale | K17: 0.05 | L17: Eva | M17: 2631.804 | N17: Gift Card | O17: FREESHIP | P17: 0 | Q17: REG100015 | R17: Cust 7037 | S17: 8.11 | T17: 45788 | U17: 45794 | V17: Wendy | W17: =M17*(1-K17) -> 2500.2138 | X17: =G17*H17 -> 2770.32 | Y17: =X17-W17 -> 270.1062 | Z17: =IF(K17=0,"No Discount",IF(K17<5%,"Low",IF(K17<15%,"Medium","High"))) -> Medium | AA17: =DATE(YEAR(Table1[[#This Row],[OrderDate]]),MONTH(Table1[[#This Row],[OrderDate]]),1) -> 45778
A18: 44983 | B18: West | C18: Laptop | D18: =TRIM(Table1[[#This Row],[Product]]) -> Laptop | E18: =PROPER(Table1[[#This Row],[Column1]]) -> Laptop | F18: =IF(OR(E18="Chair",E18="Desk"),"Furniture",IF(OR(E18="Laptop",E18="Monitor",E18="Phone",E18="Tablet"),"Technology",IF(E18="Printer","Office Supplies","Other"))) -> Technology | G18: 19 | H18: 236.11 | I18: Store D | J18: Wholesale | K18: 0 | L18: Bob | M18: 4486.09 | N18: Online | O18: WINTER15 | P18: 0 | Q18: REG100016 | R18: Cust 4975 | S18: 34.11 | T18: 44983 | U18: 44989 | V18: Wendy | W18: =M18*(1-K18) -> 4486.09 | X18: =G18*H18 -> 4486.09 | Y18: =X18-W18 -> 0 | Z18: =IF(K18=0,"No Discount",IF(K18<5%,"Low",IF(K18<15%,"Medium","High"))) -> No Discount | AA18: =DATE(YEAR(Table1[[#This Row],[OrderDate]]),MONTH(Table1[[#This Row],[OrderDate]]),1) -> 44958
A19: 45440 | B19: Central | C19: Desk | D19: =TRIM(Table1[[#This Row],[Product]]) -> Desk | E19: =PROPER(Table1[[#This Row],[Column1]]) -> Desk | F19: =IF(OR(E19="Chair",E19="Desk"),"Furniture",IF(OR(E19="Laptop",E19="Monitor",E19="Phone",E19="Tablet"),"Technology",IF(E19="Printer","Office Supplies","Other"))) -> Furniture | G19: 11 | H19: 573.14 | I19: Store D | J19: Retail | K19: 0.05 | L19: Diana | M19: 5989.313 | N19: Cash | O19: SAVE10 | P19: 0 | Q19: REG100017 | R19: Cust 8014 | S19: 34.71 | T19: 45440 | U19: 45444 | V19: Cameron | W19: =M19*(1-K19) -> 5689.8474 | X19: =G19*H19 -> 6304.54 | Y19: =X19-W19 -> 614.69265 | Z19: =IF(K19=0,"No Discount",IF(K19<5%,"Low",IF(K19<15%,"Medium","High"))) -> Medium | AA19: =DATE(YEAR(Table1[[#This Row],[OrderDate]]),MONTH(Table1[[#This Row],[OrderDate]]),1) -> 45413
A20: 45260 | B20: East | C20: Phone | D20: =TRIM(Table1[[#This Row],[Product]]) -> Phone | E20: =PROPER(Table1[[#This Row],[Column1]]) -> Phone | F20: =IF(OR(E20="Chair",E20="Desk"),"Furniture",IF(OR(E20="Laptop",E20="Monitor",E20="Phone",E20="Tablet"),"Technology",IF(E20="Printer","Office Supplies","Other"))) -> Technology | G20: 20 | H20: 519.04 | I20: Store B | J20: Retail | K20: 0.15 | L20: Carlos | M20: 8823.68 | N20: Gift Card | O20: FREESHIP | P20: 0 | Q20: REG100018 | R20: Cust 1228 | S20: 19.43 | T20: 45260 | U20: 45268 | V20: Eric | W20: =M20*(1-K20) -> 7500.128 | X20: =G20*H20 -> 10380.8 | Y20: =X20-W20 -> 2880.672 | Z20: =IF(K20=0,"No Discount",IF(K20<5%,"Low",IF(K20<15%,"Medium","High"))) -> High | AA20: =DATE(YEAR(Table1[[#This Row],[OrderDate]]),MONTH(Table1[[#This Row],[OrderDate]]),1) -> 45231
A21: 45099 | B21: West | C21: Desk | D21: =TRIM(Table1[[#This Row],[Product]]) -> Desk | E21: =PROPER(Table1[[#This Row],[Column1]]) -> Desk | F21: =IF(OR(E21="Chair",E21="Desk"),"Furniture",IF(OR(E21="Laptop",E21="Monitor",E21="Phone",E21="Tablet"),"Technology",IF(E21="Printer","Office Supplies","Other"))) -> Furniture | G21: 14 | H21: 30.83 | I21: Store B | J21: Retail | K21: 0 | L21: Carlos | M21: 431.62 | N21: Online | O21: WINTER15 | P21: 1 | Q21: REG100019 | R21: Cust 4247 | S21: 7.1 | T21: 45099 | U21: 45109 | V21: Wendy | W21: =M21*(1-K21) -> 431.62 | X21: =G21*H21 -> 431.62 | Y21: =X21-W21 -> 0 | Z21: =IF(K21=0,"No Discount",IF(K21<5%,"Low",IF(K21<15%,"Medium","High"))) -> No Discount | AA21: =DATE(YEAR(Table1[[#This Row],[OrderDate]]),MONTH(Table1[[#This Row],[OrderDate]]),1) -> 45078
A22: 45813 | B22: West | C22: Phone | D22: =TRIM(Table1[[#This Row],[Product]]) -> Phone | E22: =PROPER(Table1[[#This Row],[Column1]]) -> Phone | F22: =IF(OR(E22="Chair",E22="Desk"),"Furniture",IF(OR(E22="Laptop",E22="Monitor",E22="Phone",E22="Tablet"),"Technology",IF(E22="Printer","Office Supplies","Other"))) -> Technology | G22: 10 | H22: 319.05 | I22: Store D | J22: Wholesale | K22: 0 | L22: Diana | M22: 3190.5 | N22: Online | P22: 0 | Q22: REG100020 | R22: Cust 4199 | S22: 28.43 | T22: 45813 | U22: 45816 | V22: Wendy | W22: =M22*(1-K22) -> 3190.5 | X22: =G22*H22 -> 3190.5 | Y22: =X22-W22 -> 0 | Z22: =IF(K22=0,"No Discount",IF(K22<5%,"Low",IF(K22<15%,"Medium","High"))) -> No Discount | AA22: =DATE(YEAR(Table1[[#This Row],[OrderDate]]),MONTH(Table1[[#This Row],[OrderDate]]),1) -> 45809
A23: 44988 | B23: Central | C23: Chair | D23: =TRIM(Table1[[#This Row],[Product]]) -> Chair | E23: =PROPER(Table1[[#This Row],[Column1]]) -> Chair | F23: =IF(OR(E23="Chair",E23="Desk"),"Furniture",IF(OR(E23="Laptop",E23="Monitor",E23="Phone",E23="Tablet"),"Technology",IF(E23="Printer","Office Supplies","Other"))) -> Furniture | G23: 14 | H23: 312.79 | I23: Store A | J23: Retail | K23: 0.05 | L23: Bob | M23: 4160.107 | N23: Online | P23: 1 | Q23: REG100021 | R23: Cust 4186 | S23: 46.83 | T23: 44988 | U23: 44993 | V23: Cameron | W23: =M23*(1-K23) -> 3952.1016 | X23: =G23*H23 -> 4379.06 | Y23: =X23-W23 -> 426.95835 | Z23: =IF(K23=0,"No Discount",IF(K23<5%,"Low",IF(K23<15%,"Medium","High"))) -> Medium | AA23: =DATE(YEAR(Table1[[#This Row],[OrderDate]]),MONTH(Table1[[#This Row],[OrderDate]]),1) -> 44986
A24: 45340 | B24: North | C24: Laptop | D24: =TRIM(Table1[[#This Row],[Product]]) -> Laptop | E24: =PROPER(Table1[[#This Row],[Column1]]) -> Laptop | F24: =IF(OR(E24="Chair",E24="Desk"),"Furniture",IF(OR(E24="Laptop",E24="Monitor",E24="Phone",E24="Tablet"),"Technology",IF(E24="Printer","Office Supplies","Other"))) -> Technology | G24: 14 | H24: 395.45 | I24: Store C | J24: Retail | K24: 0 | L24: Carlos | M24: 5536.3 | N24: Cash | O24: FREESHIP | P24: 1 | Q24: REG100022 | R24: Cust 8137 | S24: 36.45 | T24: 45340 | U24: 45344 | V24: Ryan | W24: =M24*(1-K24) -> 5536.3 | X24: =G24*H24 -> 5536.3 | Y24: =X24-W24 -> 0 | Z24: =IF(K24=0,"No Discount",IF(K24<5%,"Low",IF(K24<15%,"Medium","High"))) -> No Discount | AA24: =DATE(YEAR(Table1[[#This Row],[OrderDate]]),MONTH(Table1[[#This Row],[OrderDate]]),1) -> 45323
A25: 45144 | B25: Central | C25: Laptop | D25: =TRIM(Table1[[#This Row],[Product]]) -> Laptop | E25: =PROPER(Table1[[#This Row],[Column1]]) -> Laptop | F25: =IF(OR(E25="Chair",E25="Desk"),"Furniture",IF(OR(E25="Laptop",E25="Monitor",E25="Phone",E25="Tablet"),"Technology",IF(E25="Printer","Office Supplies","Other"))) -> Technology | G25: 12 | H25: 472.72 | I25: Store D | J25: Retail | K25: 0.15 | L25: Diana | M25: 4821.744 | N25: Credit Card | P25: 0 | Q25: REG100023 | R25: Cust 4638 | S25: 27.97 | T25: 45144 | U25: 45152 | V25: Cameron | W25: =M25*(1-K25) -> 4098.4824 | X25: =G25*H25 -> 5672.64 | Y25: =X25-W25 -> 1574.1576 | Z25: =IF(K25=0,"No Discount",IF(K25<5%,"Low",IF(K25<15%,"Medium","High"))) -> High | AA25: =DATE(YEAR(Table1[[#This Row],[OrderDate]]),MONTH(Table1[[#This Row],[OrderDate]]),1) -> 45139
A26: 45435 | B26: North | C26: Desk | D26: =TRIM(Table1[[#This Row],[Product]]) -> Desk | E26: =PROPER(Table1[[#This Row],[Column1]]) -> Desk | F26: =IF(OR(E26="Chair",E26="Desk"),"Furniture",IF(OR(E26="Laptop",E26="Monitor",E26="Phone",E26="Tablet"),"Technology",IF(E26="Printer","Office Supplies","Other"))) -> Furniture | G26: 5 | H26: 288.01 | I26: Store A | J26: Wholesale | K26: 0 | L26: Eva | M26: 1440.05 | N26: Credit Card | O26: FREESHIP | P26: 0 | Q26: REG100024 | R26: Cust 8538 | S26: 46.69 | T26: 45435 | U26: 45442 | V26: Ryan | W26: =M26*(1-K26) -> 1440.05 | X26: =G26*H26 -> 1440.05 | Y26: =X26-W26 -> 0 | Z26: =IF(K26=0,"No Discount",IF(K26<5%,"Low",IF(K26<15%,"Medium","High"))) -> No Discount | AA26: =DATE(YEAR(Table1[[#This Row],[OrderDate]]),MONTH(Table1[[#This Row],[OrderDate]]),1) -> 45413
A27: 45222 | B27: East | C27: Phone | D27: =TRIM(Table1[[#This Row],[Product]]) -> Phone | E27: =PROPER(Table1[[#This Row],[Column1]]) -> Phone | F27: =IF(OR(E27="Chair",E27="Desk"),"Furniture",IF(OR(E27="Laptop",E27="Monitor",E27="Phone",E27="Tablet"),"Technology",IF(E27="Printer","Office Supplies","Other"))) -> Technology | G27: 13 | H27: 562.29 | I27: Store D | J27: Retail | K27: 0 | L27: Diana | M27: 7309.77 | N27: Gift Card | O27: SAVE10 | P27: 0 | Q27: REG100025 | R27: Cust 6322 | S27: 38.13 | T27: 45222 | U27: 45227 | V27: Eric | W27: =M27*(1-K27) -> 7309.77 | X27: =G27*H27 -> 7309.77 | Y27: =X27-W27 -> 0 | Z27: =IF(K27=0,"No Discount",IF(K27<5%,"Low",IF(K27<15%,"Medium","High"))) -> No Discount | AA27: =DATE(YEAR(Table1[[#This Row],[OrderDate]]),MONTH(Table1[[#This Row],[OrderDate]]),1) -> 45200
A28: 45824 | B28: West | C28: Phone | D28: =TRIM(Table1[[#This Row],[Product]]) -> Phone | E28: =PROPER(Table1[[#This Row],[Column1]]) -> Phone | F28: =IF(OR(E28="Chair",E28="Desk"),"Furniture",IF(OR(E28="Laptop",E28="Monitor",E28="Phone",E28="Tablet"),"Technology",IF(E28="Printer","Office Supplies","Other"))) -> Technology | G28: 1 | H28: 101.73 | I28: Store D | J28: Retail | K28: 0 | L28: Frank | M28: 101.73 | N28: Debit Card | O28: WINTER15 | P28: 0 | Q28: REG100026 | R28: Cust 2609 | S28: 11.59 | T28: 45824 | U28: 45833 | V28: Wendy | W28: =M28*(1-K28) -> 101.73 | X28: =G28*H28 -> 101.73 | Y28: =X28-W28 -> 0 | Z28: =IF(K28=0,"No Discount",IF(K28<5%,"Low",IF(K28<15%,"Medium","High"))) -> No Discount | AA28: =DATE(YEAR(Table1[[#This Row],[OrderDate]]),MONTH(Table1[[#This Row],[OrderDate]]),1) -> 45809
A29: 44988 | B29: North | C29: Phone | D29: =TRIM(Table1[[#This Row],[Product]]) -> Phone | E29: =PROPER(Table1[[#This Row],[Column1]]) -> Phone | F29: =IF(OR(E29="Chair",E29="Desk"),"Furniture",IF(OR(E29="Laptop",E29="Monitor",E29="Phone",E29="Tablet"),"Technology",IF(E29="Printer","Office Supplies","Other"))) -> Technology | G29: 4 | H29: 279.49 | I29: Store B | J29: Retail | K29: 0 | L29: Diana | M29: 1117.96 | N29: Credit Card | O29: FREESHIP | P29: 0 | Q29: REG100027 | R29: Cust 6880 | S29: 24.78 | T29: 44988 | U29: 44993 | V29: Ryan | W29: =M29*(1-K29) -> 1117.96 | X29: =G29*H29 -> 1117.96 | Y29: =X29-W29 -> 0 | Z29: =IF(K29=0,"No Discount",IF(K29<5%,"Low",IF(K29<15%,"Medium","High"))) -> No Discount | AA29: =DATE(YEAR(Table1[[#This Row],[OrderDate]]),MONTH(Table1[[#This Row],[OrderDate]]),1) -> 44986
A30: 45614 | B30: South | C30: Laptop | D30: =TRIM(Table1[[#This Row],[Product]]) -> Laptop | E30: =PROPER(Table1[[#This Row],[Column1]]) -> Laptop | F30: =IF(OR(E30="Chair",E30="Desk"),"Furniture",IF(OR(E30="Laptop",E30="Monitor",E30="Phone",E30="Tablet"),"Technology",IF(E30="Printer","Office Supplies","Other"))) -> Technology | G30: 1 | H30: 178.55 | I30: Store A | J30: Retail | K30: 0.15 | L30: Carlos | M30: 151.7675 | N30: Debit Card | O30: SAVE10 | P30: 1 | Q30: REG100028 | R30: Cust 1997 | S30: 7.61 | T30: 45614 | U30: 45617 | V30: Sophie | W30: =M30*(1-K30) -> 129.00238 | X30: =G30*H30 -> 178.55 | Y30: =X30-W30 -> 49.547625 | Z30: =IF(K30=0,"No Discount",IF(K30<5%,"Low",IF(K30<15%,"Medium","High"))) -> High | AA30: =DATE(YEAR(Table1[[#This Row],[OrderDate]]),MONTH(Table1[[#This Row],[OrderDate]]),1) -> 45597
A31: 45055 | B31: Central | C31: Tablet | D31: =TRIM(Table1[[#This Row],[Product]]) -> Tablet | E31: =PROPER(Table1[[#This Row],[Column1]]) -> Tablet | F31: =IF(OR(E31="Chair",E31="Desk"),"Furniture",IF(OR(E31="Laptop",E31="Monitor",E31="Phone",E31="Tablet"),"Technology",IF(E31="Printer","Office Supplies","Other"))) -> Technology | G31: 1 | H31: 472.07 | I31: Store A | J31: Wholesale | K31: 0.1 | L31: Carlos | M31: 424.863 | N31: Online | O31: FREESHIP | P31: 0 | Q31: REG100029 | R31: Cust 7072 | S31: 33.17 | T31: 45055 | U31: 45063 | V31: Cameron | W31: =M31*(1-K31) -> 382.3767 | X31: =G31*H31 -> 472.07 | Y31: =X31-W31 -> 89.6933 | Z31: =IF(K31=0,"No Discount",IF(K31<5%,"Low",IF(K31<15%,"Medium","High"))) -> Medium | AA31: =DATE(YEAR(Table1[[#This Row],[OrderDate]]),MONTH(Table1[[#This Row],[OrderDate]]),1) -> 45047
A32: 45633 | B32: North | C32: Tablet | D32: =TRIM(Table1[[#This Row],[Product]]) -> Tablet | E32: =PROPER(Table1[[#This Row],[Column1]]) -> Tablet | F32: =IF(OR(E32="Chair",E32="Desk"),"Furniture",IF(OR(E32="Laptop",E32="Monitor",E32="Phone",E32="Tablet"),"Technology",IF(E32="Printer","Office Supplies","Other"))) -> Technology | G32: 12 | H32: 306.29 | I32: Store D | J32: Retail | K32: 0 | L32: Frank | M32: 3675.48 | N32: Debit Card | O32: SAVE10 | P32: 0 | Q32: REG100030 | R32: Cust 7201 | S32: 37.38 | T32: 45633 | U32: 45640 | V32: Ryan | W32: =M32*(1-K32) -> 3675.48 | X32: =G32*H32 -> 3675.48 | Y32: =X32-W32 -> 0 | Z32: =IF(K32=0,"No Discount",IF(K32<5%,"Low",IF(K32<15%,"Medium","High"))) -> No Discount | AA32: =DATE(YEAR(Table1[[#This Row],[OrderDate]]),MONTH(Table1[[#This Row],[OrderDate]]),1) -> 45627
A33: 45335 | B33: North | C33: Phone | D33: =TRIM(Table1[[#This Row],[Product]]) -> Phone | E33: =PROPER(Table1[[#This Row],[Column1]]) -> Phone | F33: =IF(OR(E33="Chair",E33="Desk"),"Furniture",IF(OR(E33="Laptop",E33="Monitor",E33="Phone",E33="Tablet"),"Technology",IF(E33="Printer","Office Supplies","Other"))) -> Technology | G33: 7 | H33: 434.77 | I33: Store C | J33: Retail | K33: 0.15 | L33: Frank | M33: 2586.8815 | N33: Online | O33: SAVE10 | P33: 0 | Q33: REG100031 | R33: Cust 9923 | S33: 12.35 | T33: 45335 | U33: 45337 | V33: Ryan | W33: =M33*(1-K33) -> 2198.8493 | X33: =G33*H33 -> 3043.39 | Y33: =X33-W33 -> 844.54072 | Z33: =IF(K33=0,"No Discount",IF(K33<5%,"Low",IF(K33<15%,"Medium","High"))) -> High | AA33: =DATE(YEAR(Table1[[#This Row],[OrderDate]]),MONTH(Table1[[#This Row],[OrderDate]]),1) -> 45323
A34: 45725 | B34: South | C34: Desk | D34: =TRIM(Table1[[#This Row],[Product]]) -> Desk | E34: =PROPER(Table1[[#This Row],[Column1]]) -> Desk | F34: =IF(OR(E34="Chair",E34="Desk"),"Furniture",IF(OR(E34="Laptop",E34="Monitor",E34="Phone",E34="Tablet"),"Technology",IF(E34="Printer","Office Supplies","Other"))) -> Furniture | G34: 6 | H34: 64.98 | I34: Store C | J34: Retail | K34: 0 | L34: Carlos | M34: 389.88 | N34: Debit Card | O34: WINTER15 | P34: 0 | Q34: REG100032 | R34: Cust 2205 | S34: 21.25 | T34: 45725 | U34: 45731 | V34: Sophie | W34: =M34*(1-K34) -> 389.88 | X34: =G34*H34 -> 389.88 | Y34: =X34-W34 -> 0 | Z34: =IF(K34=0,"No Discount",IF(K34<5%,"Low",IF(K34<15%,"Medium","High"))) -> No Discount | AA34: =DATE(YEAR(Table1[[#This Row],[OrderDate]]),MONTH(Table1[[#This Row],[OrderDate]]),1) -> 45717
A35: 45021 | B35: Central | C35: Desk | D35: =TRIM(Table1[[#This Row],[Product]]) -> Desk | E35: =PROPER(Table1[[#This Row],[Column1]]) -> Desk | F35: =IF(OR(E35="Chair",E35="Desk"),"Furniture",IF(OR(E35="Laptop",E35="Monitor",E35="Phone",E35="Tablet"),"Technology",IF(E35="Printer","Office Supplies","Other"))) -> Furniture | G35: 17 | H35: 476.49 | I35: Store D | J35: Retail | K35: 0 | L35: Alice | M35: 8100.33 | N35: Gift Card | P35: 0 | Q35: REG100033 | R35: Cust 6403 | S35: 17.91 | T35: 45021 | U35: 45027 | V35: Cameron | W35: =M35*(1-K35) -> 8100.33 | X35: =G35*H35 -> 8100.33 | Y35: =X35-W35 -> 0 | Z35: =IF(K35=0,"No Discount",IF(K35<5%,"Low",IF(K35<15%,"Medium","High"))) -> No Discount | AA35: =DATE(YEAR(Table1[[#This Row],[OrderDate]]),MONTH(Table1[[#This Row],[OrderDate]]),1) -> 45017
A36: 45785 | B36: North | C36: Monitor | D36: =TRIM(Table1[[#This Row],[Product]]) -> Monitor | E36: =PROPER(Table1[[#This Row],[Column1]]) -> Monitor | F36: =IF(OR(E36="Chair",E36="Desk"),"Furniture",IF(OR(E36="Laptop",E36="Monitor",E36="Phone",E36="Tablet"),"Technology",IF(E36="Printer","Office Supplies","Other"))) -> Technology | G36: 4 | H36: 559.72 | I36: Store D | J36: Retail | K36: 0.15 | L36: Diana | M36: 1903.048 | N36: Online | O36: SAVE10 | P36: 0 | Q36: REG100034 | R36: Cust 3953 | S36: 41.91 | T36: 45785 | U36: 45789 | V36: Ryan | W36: =M36*(1-K36) -> 1617.5908 | X36: =G36*H36 -> 2238.88 | Y36: =X36-W36 -> 621.2892 | Z36: =IF(K36=0,"No Discount",IF(K36<5%,"Low",IF(K36<15%,"Medium","High"))) -> High | AA36: =DATE(YEAR(Table1[[#This Row],[OrderDate]]),MONTH(Table1[[#This Row],[OrderDate]]),1) -> 45778
A37: 45172 | B37: North | C37: Tablet | D37: =TRIM(Table1[[#This Row],[Product]]) -> Tablet | E37: =PROPER(Table1[[#This Row],[Column1]]) -> Tablet | F37: =IF(OR(E37="Chair",E37="Desk"),"Furniture",IF(OR(E37="Laptop",E37="Monitor",E37="Phone",E37="Tablet"),"Technology",IF(E37="Printer","Office Supplies","Other"))) -> Technology | G37: 14 | H37: 82.14 | I37: Store C | J37: Retail | K37: 0 | L37: Alice | M37: 1149.96 | N37: Credit Card | P37: 0 | Q37: REG100035 | R37: Cust 7902 | S37: 12.57 | T37: 45172 | U37: 45180 | V37: Ryan | W37: =M37*(1-K37) -> 1149.96 | X37: =G37*H37 -> 1149.96 | Y37: =X37-W37 -> 0 | Z37: =IF(K37=0,"No Discount",IF(K37<5%,"Low",IF(K37<15%,"Medium","High"))) -> No Discount | AA37: =DATE(YEAR(Table1[[#This Row],[OrderDate]]),MONTH(Table1[[#This Row],[OrderDate]]),1) -> 45170
A38: 45737 | B38: Central | C38: Chair | D38: =TRIM(Table1[[#This Row],[Product]]) -> Chair | E38: =PROPER(Table1[[#This Row],[Column1]]) -> Chair | F38: =IF(OR(E38="Chair",E38="Desk"),"Furniture",IF(OR(E38="Laptop",E38="Monitor",E38="Phone",E38="Tablet"),"Technology",IF(E38="Printer","Office Supplies","Other"))) -> Furniture | G38: 9 | H38: 343.21 | I38: Store A | J38: Retail | K38: 0.05 | L38: Carlos | M38: 2934.4455 | N38: Debit Card | O38: FREESHIP | P38: 0 | Q38: REG100036 | R38: Cust 9968 | S38: 40.29 | T38: 45737 | U38: 45744 | V38: Cameron | W38: =M38*(1-K38) -> 2787.7232 | X38: =G38*H38 -> 3088.89 | Y38: =X38-W38 -> 301.16678 | Z38: =IF(K38=0,"No Discount",IF(K38<5%,"Low",IF(K38<15%,"Medium","High"))) -> Medium | AA38: =DATE(YEAR(Table1[[#This Row],[OrderDate]]),MONTH(Table1[[#This Row],[OrderDate]]),1) -> 45717
A39: 45828 | B39: South | C39: Chair | D39: =TRIM(Table1[[#This Row],[Product]]) -> Chair | E39: =PROPER(Table1[[#This Row],[Column1]]) -> Chair | F39: =IF(OR(E39="Chair",E39="Desk"),"Furniture",IF(OR(E39="Laptop",E39="Monitor",E39="Phone",E39="Tablet"),"Technology",IF(E39="Printer","Office Supplies","Other"))) -> Furniture | G39: 7 | H39: 301.01 | I39: Store B | J39: Retail | K39: 0.15 | L39: Diana | M39: 1791.0095 | N39: Cash | O39: SAVE10 | P39: 1 | Q39: REG100037 | R39: Cust 3787 | S39: 34.97 | T39: 45828 | U39: 45838 | V39: Sophie | W39: =M39*(1-K39) -> 1522.3581 | X39: =G39*H39 -> 2107.07 | Y39: =X39-W39 -> 584.71192 | Z39: =IF(K39=0,"No Discount",IF(K39<5%,"Low",IF(K39<15%,"Medium","High"))) -> High | AA39: =DATE(YEAR(Table1[[#This Row],[OrderDate]]),MONTH(Table1[[#This Row],[OrderDate]]),1) -> 45809
A40: 45337 | B40: Central | C40: Printer | D40: =TRIM(Table1[[#This Row],[Product]]) -> Printer | E40: =PROPER(Table1[[#This Row],[Column1]]) -> Printer | F40: =IF(OR(E40="Chair",E40="Desk"),"Furniture",IF(OR(E40="Laptop",E40="Monitor",E40="Phone",E40="Tablet"),"Technology",IF(E40="Printer","Office Supplies","Other"))) -> Office Supplies | G40: 14 | H40: 428.13 | I40: Store C | J40: Retail | K40: 0.1 | L40: Bob | M40: 5394.438 | N40: Cash | P40: 1 | Q40: REG100038 | R40: Cust 2469 | S40: 24.77 | T40: 45337 | U40: 45347 | V40: Cameron | W40: =M40*(1-K40) -> 4854.9942 | X40: =G40*H40 -> 5993.82 | Y40: =X40-W40 -> 1138.8258 | Z40: =IF(K40=0,"No Discount",IF(K40<5%,"Low",IF(K40<15%,"Medium","High"))) -> Medium | AA40: =DATE(YEAR(Table1[[#This Row],[OrderDate]]),MONTH(Table1[[#This Row],[OrderDate]]),1) -> 45323
A41: 45086 | B41: Central | C41: Laptop | D41: =TRIM(Table1[[#This Row],[Product]]) -> Laptop | E41: =PROPER(Table1[[#This Row],[Column1]]) -> Laptop | F41: =IF(OR(E41="Chair",E41="Desk"),"Furniture",IF(OR(E41="Laptop",E41="Monitor",E41="Phone",E41="Tablet"),"Technology",IF(E41="Printer","Office Supplies","Other"))) -> Technology | G41: 2 | H41: 503.28 | I41: Store D | J41: Retail | K41: 0.15 | L41: Alice | M41: 855.576 | N41: Gift Card | P41: 0 | Q41: REG100039 | R41: Cust 6468 | S41: 34.79 | T41: 45086 | U41: 45094 | V41: Cameron | W41: =M41*(1-K41) -> 727.2396 | X41: =G41*H41 -> 1006.56 | Y41: =X41-W41 -> 279.3204 | Z41: =IF(K41=0,"No Discount",IF(K41<5%,"Low",IF(K41<15%,"Medium","High"))) -> High | AA41: =DATE(YEAR(Table1[[#This Row],[OrderDate]]),MONTH(Table1[[#This Row],[OrderDate]]),1) -> 45078
A42: 45148 | B42: South | C42: Printer | D42: =TRIM(Table1[[#This Row],[Product]]) -> Printer | E42: =PROPER(Table1[[#This Row],[Column1]]) -> Printer | F42: =IF(OR(E42="Chair",E42="Desk"),"Furniture",IF(OR(E42="Laptop",E42="Monitor",E42="Phone",E42="Tablet"),"Technology",IF(E42="Printer","Office Supplies","Other"))) -> Office Supplies | G42: 5 | H42: 470.32 | I42: Store A | J42: Retail | K42: 0.1 | L42: Eva | M42: 2116.44 | N42: Debit Card | O42: SAVE10 | P42: 0 | Q42: REG100040 | R42: Cust 5312 | S42: 17.77 | T42: 45148 | U42: 45152 | V42: Sophie | W42: =M42*(1-K42) -> 1904.796 | X42: =G42*H42 -> 2351.6 | Y42: =X42-W42 -> 446.804 | Z42: =IF(K42=0,"No Discount",IF(K42<5%,"Low",IF(K42<15%,"Medium","High"))) -> Medium | AA42: =DATE(YEAR(Table1[[#This Row],[OrderDate]]),MONTH(Table1[[#This Row],[OrderDate]]),1) -> 45139
A43: 45459 | B43: Central | C43: Printer | D43: =TRIM(Table1[[#This Row],[Product]]) -> Printer | E43: =PROPER(Table1[[#This Row],[Column1]]) -> Printer | F43: =IF(OR(E43="Chair",E43="Desk"),"Furniture",IF(OR(E43="Laptop",E43="Monitor",E43="Phone",E43="Tablet"),"Technology",IF(E43="Printer","Office Supplies","Other"))) -> Office Supplies | G43: 20 | H43: 65.17 | I43: Store C | J43: Wholesale | K43: 0.05 | L43: Eva | M43: 1238.23 | N43: Gift Card | O43: FREESHIP | P43: 0 | Q43: REG100041 | R43: Cust 1482 | S43: 21.72 | T43: 45459 | U43: 45468 | V43: Cameron | W43: =M43*(1-K43) -> 1176.3185 | X43: =G43*H43 -> 1303.4 | Y43: =X43-W43 -> 127.0815 | Z43: =IF(K43=0,"No Discount",IF(K43<5%,"Low",IF(K43<15%,"Medium","High"))) -> Medium | AA43: =DATE(YEAR(Table1[[#This Row],[OrderDate]]),MONTH(Table1[[#This Row],[OrderDate]]),1) -> 45444
A44: 45130 | B44: South | C44: Laptop | D44: =TRIM(Table1[[#This Row],[Product]]) -> Laptop | E44: =PROPER(Table1[[#This Row],[Column1]]) -> Laptop | F44: =IF(OR(E44="Chair",E44="Desk"),"Furniture",IF(OR(E44="Laptop",E44="Monitor",E44="Phone",E44="Tablet"),"Technology",IF(E44="Printer","Office Supplies","Other"))) -> Technology | G44: 12 | H44: 36.17 | I44: Store A | J44: Retail | K44: 0 | L44: Eva | M44: 434.04 | N44: Online | O44: WINTER15 | P44: 0 | Q44: REG100042 | R44: Cust 7903 | S44: 34.85 | T44: 45130 | U44: 45133 | V44: Sophie | W44: =M44*(1-K44) -> 434.04 | X44: =G44*H44 -> 434.04 | Y44: =X44-W44 -> 0 | Z44: =IF(K44=0,"No Discount",IF(K44<5%,"Low",IF(K44<15%,"Medium","High"))) -> No Discount | AA44: =DATE(YEAR(Table1[[#This Row],[OrderDate]]),MONTH(Table1[[#This Row],[OrderDate]]),1) -> 45108
A45: 45066 | B45: Central | C45: Printer | D45: =TRIM(Table1[[#This Row],[Product]]) -> Printer | E45: =PROPER(Table1[[#This Row],[Column1]]) -> Printer | F45: =IF(OR(E45="Chair",E45="Desk"),"Furniture",IF(OR(E45="Laptop",E45="Monitor",E45="Phone",E45="Tablet"),"Technology",IF(E45="Printer","Office Supplies","Other"))) -> Office Supplies | G45: 4 | H45: 459.31 | I45: Store D | J45: Wholesale | K45: 0.15 | L45: Carlos | M45: 1561.654 | N45: Gift Card | O45: WINTER15 | P45: 1 | Q45: REG100043 | R45: Cust 9605 | S45: 27.39 | T45: 45066 | U45: 45073 | V45: Cameron | W45: =M45*(1-K45) -> 1327.4059 | X45: =G45*H45 -> 1837.24 | Y45: =X45-W45 -> 509.8341 | Z45: =IF(K45=0,"No Discount",IF(K45<5%,"Low",IF(K45<15%,"Medium","High"))) -> High | AA45: =DATE(YEAR(Table1[[#This Row],[OrderDate]]),MONTH(Table1[[#This Row],[OrderDate]]),1) -> 45047
A46: 45107 | B46: South | C46: Laptop | D46: =TRIM(Table1[[#This Row],[Product]]) -> Laptop | E46: =PROPER(Table1[[#This Row],[Column1]]) -> Laptop | F46: =IF(OR(E46="Chair",E46="Desk"),"Furniture",IF(OR(E46="Laptop",E46="Monitor",E46="Phone",E46="Tablet"),"Technology",IF(E46="Printer","Office Supplies","Other"))) -> Technology | G46: 2 | H46: 416.06 | I46: Store D | J46: Retail | K46: 0.05 | L46: Eva | M46: 790.514 | N46: Debit Card | O46: SAVE10 | P46: 0 | Q46: REG100044 | R46: Cust 3298 | S46: 11.62 | T46: 45107 | U46: 45111 | V46: Sophie | W46: =M46*(1-K46) -> 750.9883 | X46: =G46*H46 -> 832.12 | Y46: =X46-W46 -> 81.1317 | Z46: =IF(K46=0,"No Discount",IF(K46<5%,"Low",IF(K46<15%,"Medium","High"))) -> Medium | AA46: =DATE(YEAR(Table1[[#This Row],[OrderDate]]),MONTH(Table1[[#This Row],[OrderDate]]),1) -> 45078
A47: 45447 | B47: South | C47: Tablet | D47: =TRIM(Table1[[#This Row],[Product]]) -> Tablet | E47: =PROPER(Table1[[#This Row],[Column1]]) -> Tablet | F47: =IF(OR(E47="Chair",E47="Desk"),"Furniture",IF(OR(E47="Laptop",E47="Monitor",E47="Phone",E47="Tablet"),"Technology",IF(E47="Printer","Office Supplies","Other"))) -> Technology | G47: 16 | H47: 302.58 | I47: Store D | J47: Retail | K47: 0 | L47: Alice | M47: 4841.28 | N47: Online | O47: WINTER15 | P47: 1 | Q47: REG100045 | R47: Cust 5533 | S47: 20.76 | T47: 45447 | U47: 45457 | V47: Sophie | W47: =M47*(1-K47) -> 4841.28 | X47: =G47*H47 -> 4841.28 | Y47: =X47-W47 -> 0 | Z47: =IF(K47=0,"No Discount",IF(K47<5%,"Low",IF(K47<15%,"Medium","High"))) -> No Discount | AA47: =DATE(YEAR(Table1[[#This Row],[OrderDate]]),MONTH(Table1[[#This Row],[OrderDate]]),1) -> 45444
A48: 45691 | B48: West | C48: Chair | D48: =TRIM(Table1[[#This Row],[Product]]) -> Chair | E48: =PROPER(Table1[[#This Row],[Column1]]) -> Chair | F48: =IF(OR(E48="Chair",E48="Desk"),"Furniture",IF(OR(E48="Laptop",E48="Monitor",E48="Phone",E48="Tablet"),"Technology",IF(E48="Printer","Office Supplies","Other"))) -> Furniture | G48: 11 | H48: 33.13 | I48: Store A | J48: Retail | K48: 0.15 | L48: Frank | M48: 309.7655 | N48: Online | O48: FREESHIP | P48: 0 | Q48: REG100046 | R48: Cust 6362 | S48: 24.95 | T48: 45691 | U48: 45693 | V48: Wendy | W48: =M48*(1-K48) -> 263.30067 | X48: =G48*H48 -> 364.43 | Y48: =X48-W48 -> 101.12933 | Z48: =IF(K48=0,"No Discount",IF(K48<5%,"Low",IF(K48<15%,"Medium","High"))) -> High | AA48: =DATE(YEAR(Table1[[#This Row],[OrderDate]]),MONTH(Table1[[#This Row],[OrderDate]]),1) -> 45689
A49: 45300 | B49: East | C49: Tablet | D49: =TRIM(Table1[[#This Row],[Product]]) -> Tablet | E49: =PROPER(Table1[[#This Row],[Column1]]) -> Tablet | F49: =IF(OR(E49="Chair",E49="Desk"),"Furniture",IF(OR(E49="Laptop",E49="Monitor",E49="Phone",E49="Tablet"),"Technology",IF(E49="Printer","Office Supplies","Other"))) -> Technology | G49: 8 | H49: 582.52 | I49: Store D | J49: Retail | K49: 0.15 | L49: Frank | M49: 3961.136 | N49: Gift Card | O49: WINTER15 | P49: 0 | Q49: REG100047 | R49: Cust 4826 | S49: 6.47 | T49: 45300 | U49: 45304 | V49: Eric | W49: =M49*(1-K49) -> 3366.9656 | X49: =G49*H49 -> 4660.16 | Y49: =X49-W49 -> 1293.1944 | Z49: =IF(K49=0,"No Discount",IF(K49<5%,"Low",IF(K49<15%,"Medium","High"))) -> High | AA49: =DATE(YEAR(Table1[[#This Row],[OrderDate]]),MONTH(Table1[[#This Row],[OrderDate]]),1) -> 45292
A50: 45365 | B50: North | C50: Desk | D50: =TRIM(Table1[[#This Row],[Product]]) -> Desk | E50: =PROPER(Table1[[#This Row],[Column1]]) -> Desk | F50: =IF(OR(E50="Chair",E50="Desk"),"Furniture",IF(OR(E50="Laptop",E50="Monitor",E50="Phone",E50="Tablet"),"Technology",IF(E50="Printer","Office Supplies","Other"))) -> Furniture | G50: 5 | H50: 165.15 | I50: Store A | J50: Retail | K50: 0.1 | L50: Eva | M50: 743.175 | N50: Gift Card | P50: 0 | Q50: REG100048 | R50: Cust 2171 | S50: 20.57 | T50: 45365 | U50: 45367 | V50: Ryan | W50: =M50*(1-K50) -> 668.8575 | X50: =G50*H50 -> 825.75 | Y50: =X50-W50 -> 156.8925 | Z50: =IF(K50=0,"No Discount",IF(K50<5%,"Low",IF(K50<15%,"Medium","High"))) -> Medium | AA50: =DATE(YEAR(Table1[[#This Row],[OrderDate]]),MONTH(Table1[[#This Row],[OrderDate]]),1) -> 45352
A51: 45541 | B51: West | C51: Monitor | D51: =TRIM(Table1[[#This Row],[Product]]) -> Monitor | E51: =PROPER(Table1[[#This Row],[Column1]]) -> Monitor | F51: =IF(OR(E51="Chair",E51="Desk"),"Furniture",IF(OR(E51="Laptop",E51="Monitor",E51="Phone",E51="Tablet"),"Technology",IF(E51="Printer","Office Supplies","Other"))) -> Technology | G51: 14 | H51: 242.82 | I51: Store D | J51: Wholesale | K51: 0.15 | L51: Alice | M51: 2889.558 | N51: Cash | O51: WINTER15 | P51: 1 | Q51: REG100049 | R51: Cust 4005 | S51: 20.71 | T51: 45541 | U51: 45548 | V51: Wendy | W51: =M51*(1-K51) -> 2456.1243 | X51: =G51*H51 -> 3399.48 | Y51: =X51-W51 -> 943.3557 | Z51: =IF(K51=0,"No Discount",IF(K51<5%,"Low",IF(K51<15%,"Medium","High"))) -> High | AA51: =DATE(YEAR(Table1[[#This Row],[OrderDate]]),MONTH(Table1[[#This Row],[OrderDate]]),1) -> 45536
A52: 45002 | B52: East | C52: Monitor | D52: =TRIM(Table1[[#This Row],[Product]]) -> Monitor | E52: =PROPER(Table1[[#This Row],[Column1]]) -> Monitor | F52: =IF(OR(E52="Chair",E52="Desk"),"Furniture",IF(OR(E52="Laptop",E52="Monitor",E52="Phone",E52="Tablet"),"Technology",IF(E52="Printer","Office Supplies","Other"))) -> Technology | G52: 13 | H52: 65.99 | I52: Store A | J52: Wholesale | K52: 0.1 | L52: Frank | M52: 772.083 | N52: Cash | O52: WINTER15 | P52: 0 | Q52: REG100050 | R52: Cust 7032 | S52: 12.87 | T52: 45002 | U52: 45005 | V52: Eric | W52: =M52*(1-K52) -> 694.8747 | X52: =G52*H52 -> 857.87 | Y52: =X52-W52 -> 162.9953 | Z52: =IF(K52=0,"No Discount",IF(K52<5%,"Low",IF(K52<15%,"Medium","High"))) -> Medium | AA52: =DATE(YEAR(Table1[[#This Row],[OrderDate]]),MONTH(Table1[[#This Row],[OrderDate]]),1) -> 44986
A53: 45674 | B53: West | C53: Chair | D53: =TRIM(Table1[[#This Row],[Product]]) -> Chair | E53: =PROPER(Table1[[#This Row],[Column1]]) -> Chair | F53: =IF(OR(E53="Chair",E53="Desk"),"Furniture",IF(OR(E53="Laptop",E53="Monitor",E53="Phone",E53="Tablet"),"Technology",IF(E53="Printer","Office Supplies","Other"))) -> Furniture | G53: 2 | H53: 251.69 | I53: Store C | J53: Wholesale | K53: 0 | L53: Alice | M53: 503.38 | N53: Debit Card | O53: FREESHIP | P53: 0 | Q53: REG100051 | R53: Cust 7167 | S53: 42.49 | T53: 45674 | U53: 45681 | V53: Wendy | W53: =M53*(1-K53) -> 503.38 | X53: =G53*H53 -> 503.38 | Y53: =X53-W53 -> 0 | Z53: =IF(K53=0,"No Discount",IF(K53<5%,"Low",IF(K53<15%,"Medium","High"))) -> No Discount | AA53: =DATE(YEAR(Table1[[#This Row],[OrderDate]]),MONTH(Table1[[#This Row],[OrderDate]]),1) -> 45658
A54: 45547 | B54: South | C54: Laptop | D54: =TRIM(Table1[[#This Row],[Product]]) -> Laptop | E54: =PROPER(Table1[[#This Row],[Column1]]) -> Laptop | F54: =IF(OR(E54="Chair",E54="Desk"),"Furniture",IF(OR(E54="Laptop",E54="Monitor",E54="Phone",E54="Tablet"),"Technology",IF(E54="Printer","Office Supplies","Other"))) -> Technology | G54: 1 | H54: 269.41 | I54: Store B | J54: Wholesale | K54: 0.1 | L54: Eva | M54: 242.469 | N54: Cash | O54: WINTER15 | P54: 1 | Q54: REG100052 | R54: Cust 5702 | S54: 19.22 | T54: 45547 | U54: 45553 | V54: Sophie | W54: =M54*(1-K54) -> 218.2221 | X54: =G54*H54 -> 269.41 | Y54: =X54-W54 -> 51.1879 | Z54: =IF(K54=0,"No Discount",IF(K54<5%,"Low",IF(K54<15%,"Medium","High"))) -> Medium | AA54: =DATE(YEAR(Table1[[#This Row],[OrderDate]]),MONTH(Table1[[#This Row],[OrderDate]]),1) -> 45536
A55: 45296 | B55: South | C55: Monitor | D55: =TRIM(Table1[[#This Row],[Product]]) -> Monitor | E55: =PROPER(Table1[[#This Row],[Column1]]) -> Monitor | F55: =IF(OR(E55="Chair",E55="Desk"),"Furniture",IF(OR(E55="Laptop",E55="Monitor",E55="Phone",E55="Tablet"),"Technology",IF(E55="Printer","Office Supplies","Other"))) -> Technology | G55: 2 | H55: 371.3 | I55: Store B | J55: Wholesale | K55: 0.05 | L55: Bob | M55: 705.47 | N55: Credit Card | O55: SAVE10 | P55: 0 | Q55: REG100053 | R55: Cust 4944 | S55: 36.51 | T55: 45296 | U55: 45306 | V55: Sophie | W55: =M55*(1-K55) -> 670.1965 | X55: =G55*H55 -> 742.6 | Y55: =X55-W55 -> 72.4035 | Z55: =IF(K55=0,"No Discount",IF(K55<5%,"Low",IF(K55<15%,"Medium","High"))) -> Medium | AA55: =DATE(YEAR(Table1[[#This Row],[OrderDate]]),MONTH(Table1[[#This Row],[OrderDate]]),1) -> 45292
A56: 45401 | B56: West | C56: Tablet | D56: =TRIM(Table1[[#This Row],[Product]]) -> Tablet | E56: =PROPER(Table1[[#This Row],[Column1]]) -> Tablet | F56: =IF(OR(E56="Chair",E56="Desk"),"Furniture",IF(OR(E56="Laptop",E56="Monitor",E56="Phone",E56="Tablet"),"Technology",IF(E56="Printer","Office Supplies","Other"))) -> Technology | G56: 11 | H56: 288.24 | I56: Store A | J56: Wholesale | K56: 0.15 | L56: Diana | M56: 2695.044 | N56: Online | P56: 0 | Q56: REG100054 | R56: Cust 8149 | S56: 37.39 | T56: 45401 | U56: 45407 | V56: Wendy | W56: =M56*(1-K56) -> 2290.7874 | X56: =G56*H56 -> 3170.64 | Y56: =X56-W56 -> 879.8526 | Z56: =IF(K56=0,"No Discount",IF(K56<5%,"Low",IF(K56<15%,"Medium","High"))) -> High | AA56: =DATE(YEAR(Table1[[#This Row],[OrderDate]]),MONTH(Table1[[#This Row],[OrderDate]]),1) -> 45383
A57: 45819 | B57: Central | C57: Tablet | D57: =TRIM(Table1[[#This Row],[Product]]) -> Tablet | E57: =PROPER(Table1[[#This Row],[Column1]]) -> Tablet | F57: =IF(OR(E57="Chair",E57="Desk"),"Furniture",IF(OR(E57="Laptop",E57="Monitor",E57="Phone",E57="Tablet"),"Technology",IF(E57="Printer","Office Supplies","Other"))) -> Technology | G57: 11 | H57: 232.75 | I57: Store D | J57: Wholesale | K57: 0.05 | L57: Eva | M57: 2432.2375 | N57: Credit Card | O57: SAVE10 | P57: 0 | Q57: REG100055 | R57: Cust 3638 | S57: 36.33 | T57: 45819 | U57: 45829 | V57: Cameron | W57: =M57*(1-K57) -> 2310.6256 | X57: =G57*H57 -> 2560.25 | Y57: =X57-W57 -> 249.62437 | Z57: =IF(K57=0,"No Discount",IF(K57<5%,"Low",IF(K57<15%,"Medium","High"))) -> Medium | AA57: =DATE(YEAR(Table1[[#This Row],[OrderDate]]),MONTH(Table1[[#This Row],[OrderDate]]),1) -> 45809
A58: 45722 | B58: East | C58: Phone | D58: =TRIM(Table1[[#This Row],[Product]]) -> Phone | E58: =PROPER(Table1[[#This Row],[Column1]]) -> Phone | F58: =IF(OR(E58="Chair",E58="Desk"),"Furniture",IF(OR(E58="Laptop",E58="Monitor",E58="Phone",E58="Tablet"),"Technology",IF(E58="Printer","Office Supplies","Other"))) -> Technology | G58: 17 | H58: 146.28 | I58: Store B | J58: Retail | K58: 0.15 | L58: Carlos | M58: 2113.746 | N58: Cash | O58: SAVE10 | P58: 0 | Q58: REG100056 | R58: Cust 9973 | S58: 7.84 | T58: 45722 | U58: 45731 | V58: Eric | W58: =M58*(1-K58) -> 1796.6841 | X58: =G58*H58 -> 2486.76 | Y58: =X58-W58 -> 690.0759 | Z58: =IF(K58=0,"No Discount",IF(K58<5%,"Low",IF(K58<15%,"Medium","High"))) -> High | AA58: =DATE(YEAR(Table1[[#This Row],[OrderDate]]),MONTH(Table1[[#This Row],[OrderDate]]),1) -> 45717
A59: 45070 | B59: East | C59: Chair | D59: =TRIM(Table1[[#This Row],[Product]]) -> Chair | E59: =PROPER(Table1[[#This Row],[Column1]]) -> Chair | F59: =IF(OR(E59="Chair",E59="Desk"),"Furniture",IF(OR(E59="Laptop",E59="Monitor",E59="Phone",E59="Tablet"),"Technology",IF(E59="Printer","Office Supplies","Other"))) -> Furniture | G59: 5 | H59: 100.38 | I59: Store C | J59: Retail | K59: 0.1 | L59: Eva | M59: 451.71 | N59: Gift Card | O59: WINTER15 | P59: 1 | Q59: REG100057 | R59: Cust 4214 | S59: 18.35 | T59: 45070 | U59: 45072 | V59: Eric | W59: =M59*(1-K59) -> 406.539 | X59: =G59*H59 -> 501.9 | Y59: =X59-W59 -> 95.361 | Z59: =IF(K59=0,"No Discount",IF(K59<5%,"Low",IF(K59<15%,"Medium","High"))) -> Medium | AA59: =DATE(YEAR(Table1[[#This Row],[OrderDate]]),MONTH(Table1[[#This Row],[OrderDate]]),1) -> 45047
A60: 44953 | B60: South | C60: Phone | D60: =TRIM(Table1[[#This Row],[Product]]) -> Phone | E60: =PROPER(Table1[[#This Row],[Column1]]) -> Phone | F60: =IF(OR(E60="Chair",E60="Desk"),"Furniture",IF(OR(E60="Laptop",E60="Monitor",E60="Phone",E60="Tablet"),"Technology",IF(E60="Printer","Office Supplies","Other"))) -> Technology | G60: 11 | H60: 375.48 | I60: Store B | J60: Retail | K60: 0.05 | L60: Bob | M60: 3923.766 | N60: Debit Card | O60: WINTER15 | P60: 0 | Q60: REG100058 | R60: Cust 2647 | S60: 15.95 | T60: 44953 | U60: 44960 | V60: Sophie | W60: =M60*(1-K60) -> 3727.5777 | X60: =G60*H60 -> 4130.28 | Y60: =X60-W60 -> 402.7023 | Z60: =IF(K60=0,"No Discount",IF(K60<5%,"Low",IF(K60<15%,"Medium","High"))) -> Medium | AA60: =DATE(YEAR(Table1[[#This Row],[OrderDate]]),MONTH(Table1[[#This Row],[OrderDate]]),1) -> 44927
A61: 45372 | B61: South | C61: Laptop | D61: =TRIM(Table1[[#This Row],[Product]]) -> Laptop | E61: =PROPER(Table1[[#This Row],[Column1]]) -> Laptop | F61: =IF(OR(E61="Chair",E61="Desk"),"Furniture",IF(OR(E61="Laptop",E61="Monitor",E61="Phone",E61="Tablet"),"Technology",IF(E61="Printer","Office Supplies","Other"))) -> Technology | G61: 18 | H61: 316.89 | I61: Store B | J61: Wholesale | K61: 0.05 | L61: Bob | M61: 5418.819 | N61: Cash | O61: FREESHIP | P61: 0 | Q61: REG100059 | R61: Cust 3552 | S61: 15.69 | T61: 45372 | U61: 45378 | V61: Sophie | W61: =M61*(1-K61) -> 5147.8781 | X61: =G61*H61 -> 5704.02 | Y61: =X61-W61 -> 556.14195 | Z61: =IF(K61=0,"No Discount",IF(K61<5%,"Low",IF(K61<15%,"Medium","High"))) -> Medium | AA61: =DATE(YEAR(Table1[[#This Row],[OrderDate]]),MONTH(Table1[[#This Row],[OrderDate]]),1) -> 45352
A62: 45682 | B62: West | C62: Laptop | D62: =TRIM(Table1[[#This Row],[Product]]) -> Laptop | E62: =PROPER(Table1[[#This Row],[Column1]]) -> Laptop | F62: =IF(OR(E62="Chair",E62="Desk"),"Furniture",IF(OR(E62="Laptop",E62="Monitor",E62="Phone",E62="Tablet"),"Technology",IF(E62="Printer","Office Supplies","Other"))) -> Technology | G62: 20 | H62: 295.06 | I62: Store D | J62: Retail | K62: 0.15 | L62: Frank | M62: 5016.02 | N62: Online | O62: SAVE10 | P62: 1 | Q62: REG100060 | R62: Cust 3354 | S62: 13.66 | T62: 45682 | U62: 45688 | V62: Wendy | W62: =M62*(1-K62) -> 4263.617 | X62: =G62*H62 -> 5901.2 | Y62: =X62-W62 -> 1637.583 | Z62: =IF(K62=0,"No Discount",IF(K62<5%,"Low",IF(K62<15%,"Medium","High"))) -> High | AA62: =DATE(YEAR(Table1[[#This Row],[OrderDate]]),MONTH(Table1[[#This Row],[OrderDate]]),1) -> 45658
A63: 45089 | B63: Central | C63: Phone | D63: =TRIM(Table1[[#This Row],[Product]]) -> Phone | E63: =PROPER(Table1[[#This Row],[Column1]]) -> Phone | F63: =IF(OR(E63="Chair",E63="Desk"),"Furniture",IF(OR(E63="Laptop",E63="Monitor",E63="Phone",E63="Tablet"),"Technology",IF(E63="Printer","Office Supplies","Other"))) -> Technology | G63: 8 | H63: 301.68 | I63: Store D | J63: Retail | K63: 0 | L63: Eva | M63: 2413.44 | N63: Cash | O63: SAVE10 | P63: 0 | Q63: REG100061 | R63: Cust 3903 | S63: 36.54 | T63: 45089 | U63: 45098 | V63: Cameron | W63: =M63*(1-K63) -> 2413.44 | X63: =G63*H63 -> 2413.44 | Y63: =X63-W63 -> 0 | Z63: =IF(K63=0,"No Discount",IF(K63<5%,"Low",IF(K63<15%,"Medium","High"))) -> No Discount | AA63: =DATE(YEAR(Table1[[#This Row],[OrderDate]]),MONTH(Table1[[#This Row],[OrderDate]]),1) -> 45078
A64: 45738 | B64: Central | C64: Chair | D64: =TRIM(Table1[[#This Row],[Product]]) -> Chair | E64: =PROPER(Table1[[#This Row],[Column1]]) -> Chair | F64: =IF(OR(E64="Chair",E64="Desk"),"Furniture",IF(OR(E64="Laptop",E64="Monitor",E64="Phone",E64="Tablet"),"Technology",IF(E64="Printer","Office Supplies","Other"))) -> Furniture | G64: 3 | H64: 475.39 | I64: Store B | J64: Retail | K64: 0.1 | L64: Alice | M64: 1283.553 | N64: Gift Card | P64: 0 | Q64: REG100062 | R64: Cust 5358 | S64: 15.62 | T64: 45738 | U64: 45742 | V64: Cameron | W64: =M64*(1-K64) -> 1155.1977 | X64: =G64*H64 -> 1426.17 | Y64: =X64-W64 -> 270.9723 | Z64: =IF(K64=0,"No Discount",IF(K64<5%,"Low",IF(K64<15%,"Medium","High"))) -> Medium | AA64: =DATE(YEAR(Table1[[#This Row],[OrderDate]]),MONTH(Table1[[#This Row],[OrderDate]]),1) -> 45717
A65: 45346 | B65: Central | C65: Desk | D65: =TRIM(Table1[[#This Row],[Product]]) -> Desk | E65: =PROPER(Table1[[#This Row],[Column1]]) -> Desk | F65: =IF(OR(E65="Chair",E65="Desk"),"Furniture",IF(OR(E65="Laptop",E65="Monitor",E65="Phone",E65="Tablet"),"Technology",IF(E65="Printer","Office Supplies","Other"))) -> Furniture | G65: 16 | H65: 47.25 | I65: Store D | J65: Retail | K65: 0.15 | L65: Bob | M65: 642.6 | N65: Debit Card | O65: FREESHIP | P65: 0 | Q65: REG100063 | R65: Cust 8144 | S65: 29.5 | T65: 45346 | U65: 45349 | V65: Cameron | W65: =M65*(1-K65) -> 546.21 | X65: =G65*H65 -> 756 | Y65: =X65-W65 -> 209.79 | Z65: =IF(K65=0,"No Discount",IF(K65<5%,"Low",IF(K65<15%,"Medium","High"))) -> High | AA65: =DATE(YEAR(Table1[[#This Row],[OrderDate]]),MONTH(Table1[[#This Row],[OrderDate]]),1) -> 45323
A66: 45269 | B66: South | C66: Chair | D66: =TRIM(Table1[[#This Row],[Product]]) -> Chair | E66: =PROPER(Table1[[#This Row],[Column1]]) -> Chair | F66: =IF(OR(E66="Chair",E66="Desk"),"Furniture",IF(OR(E66="Laptop",E66="Monitor",E66="Phone",E66="Tablet"),"Technology",IF(E66="Printer","Office Supplies","Other"))) -> Furniture | G66: 15 | H66: 511.17 | I66: Store B | J66: Wholesale | K66: 0 | L66: Frank | M66: 7667.55 | N66: Online | O66: FREESHIP | P66: 0 | Q66: REG100064 | R66: Cust 6747 | S66: 21.77 | T66: 45269 | U66: 45272 | V66: Sophie | W66: =M66*(1-K66) -> 7667.55 | X66: =G66*H66 -> 7667.55 | Y66: =X66-W66 -> 0 | Z66: =IF(K66=0,"No Discount",IF(K66<5%,"Low",IF(K66<15%,"Medium","High"))) -> No Discount | AA66: =DATE(YEAR(Table1[[#This Row],[OrderDate]]),MONTH(Table1[[#This Row],[OrderDate]]),1) -> 45261
A67: 45200 | B67: Central | C67: Monitor | D67: =TRIM(Table1[[#This Row],[Product]]) -> Monitor | E67: =PROPER(Table1[[#This Row],[Column1]]) -> Monitor | F67: =IF(OR(E67="Chair",E67="Desk"),"Furniture",IF(OR(E67="Laptop",E67="Monitor",E67="Phone",E67="Tablet"),"Technology",IF(E67="Printer","Office Supplies","Other"))) -> Technology | G67: 3 | H67: 66.58 | I67: Store B | J67: Retail | K67: 0.1 | L67: Frank | M67: 179.766 | N67: Debit Card | O67: FREESHIP | P67: 0 | Q67: REG100065 | R67: Cust 8330 | S67: 22.43 | T67: 45200 | U67: 45204 | V67: Cameron | W67: =M67*(1-K67) -> 161.7894 | X67: =G67*H67 -> 199.74 | Y67: =X67-W67 -> 37.9506 | Z67: =IF(K67=0,"No Discount",IF(K67<5%,"Low",IF(K67<15%,"Medium","High"))) -> Medium | AA67: =DATE(YEAR(Table1[[#This Row],[OrderDate]]),MONTH(Table1[[#This Row],[OrderDate]]),1) -> 45200
A68: 45138 | B68: West | C68: Tablet | D68: =TRIM(Table1[[#This Row],[Product]]) -> Tablet | E68: =PROPER(Table1[[#This Row],[Column1]]) -> Tablet | F68: =IF(OR(E68="Chair",E68="Desk"),"Furniture",IF(OR(E68="Laptop",E68="Monitor",E68="Phone",E68="Tablet"),"Technology",IF(E68="Printer","Office Supplies","Other"))) -> Technology | G68: 5 | H68: 490.52 | I68: Store D | J68: Wholesale | K68: 0.05 | L68: Frank | M68: 2329.97 | N68: Online | P68: 0 | Q68: REG100066 | R68: Cust 7186 | S68: 12.24 | T68: 45138 | U68: 45145 | V68: Wendy | W68: =M68*(1-K68) -> 2213.4715 | X68: =G68*H68 -> 2452.6 | Y68: =X68-W68 -> 239.1285 | Z68: =IF(K68=0,"No Discount",IF(K68<5%,"Low",IF(K68<15%,"Medium","High"))) -> Medium | AA68: =DATE(YEAR(Table1[[#This Row],[OrderDate]]),MONTH(Table1[[#This Row],[OrderDate]]),1) -> 45108
A69: 45650 | B69: South | C69: Chair | D69: =TRIM(Table1[[#This Row],[Product]]) -> Chair | E69: =PROPER(Table1[[#This Row],[Column1]]) -> Chair | F69: =IF(OR(E69="Chair",E69="Desk"),"Furniture",IF(OR(E69="Laptop",E69="Monitor",E69="Phone",E69="Tablet"),"Technology",IF(E69="Printer","Office Supplies","Other"))) -> Furniture | G69: 8 | H69: 405.96 | I69: Store A | J69: Wholesale | K69: 0.05 | L69: Carlos | M69: 3085.296 | N69: Credit Card | O69: WINTER15 | P69: 0 | Q69: REG100067 | R69: Cust 8287 | S69: 41.27 | T69: 45650 | U69: 45657 | V69: Sophie | W69: =M69*(1-K69) -> 2931.0312 | X69: =G69*H69 -> 3247.68 | Y69: =X69-W69 -> 316.6488 | Z69: =IF(K69=0,"No Discount",IF(K69<5%,"Low",IF(K69<15%,"Medium","High"))) -> Medium | AA69: =DATE(YEAR(Table1[[#This Row],[OrderDate]]),MONTH(Table1[[#This Row],[OrderDate]]),1) -> 45627
A70: 45611 | B70: North | C70: Phone | D70: =TRIM(Table1[[#This Row],[Product]]) -> Phone | E70: =PROPER(Table1[[#This Row],[Column1]]) -> Phone | F70: =IF(OR(E70="Chair",E70="Desk"),"Furniture",IF(OR(E70="Laptop",E70="Monitor",E70="Phone",E70="Tablet"),"Technology",IF(E70="Printer","Office Supplies","Other"))) -> Technology | G70: 1 | H70: 159.41 | I70: Store B | J70: Retail | K70: 0.1 | L70: Bob | M70: 143.469 | N70: Credit Card | O70: FREESHIP | P70: 0 | Q70: REG100068 | R70: Cust 3986 | S70: 35.14 | T70: 45611 | U70: 45615 | V70: Ryan | W70: =M70*(1-K70) -> 129.1221 | X70: =G70*H70 -> 159.41 | Y70: =X70-W70 -> 30.2879 | Z70: =IF(K70=0,"No Discount",IF(K70<5%,"Low",IF(K70<15%,"Medium","High"))) -> Medium | AA70: =DATE(YEAR(Table1[[#This Row],[OrderDate]]),MONTH(Table1[[#This Row],[OrderDate]]),1) -> 45597
A71: 45729 | B71: West | C71: Monitor | D71: =TRIM(Table1[[#This Row],[Product]]) -> Monitor | E71: =PROPER(Table1[[#This Row],[Column1]]) -> Monitor | F71: =IF(OR(E71="Chair",E71="Desk"),"Furniture",IF(OR(E71="Laptop",E71="Monitor",E71="Phone",E71="Tablet"),"Technology",IF(E71="Printer","Office Supplies","Other"))) -> Technology | G71: 16 | H71: 38.49 | I71: Store C | J71: Retail | K71: 0.15 | L71: Carlos | M71: 523.464 | N71: Debit Card | O71: SAVE10 | P71: 0 | Q71: REG100069 | R71: Cust 3213 | S71: 8.38 | T71: 45729 | U71: 45738 | V71: Wendy | W71: =M71*(1-K71) -> 444.9444 | X71: =G71*H71 -> 615.84 | Y71: =X71-W71 -> 170.8956 | Z71: =IF(K71=0,"No Discount",IF(K71<5%,"Low",IF(K71<15%,"Medium","High"))) -> High | AA71: =DATE(YEAR(Table1[[#This Row],[OrderDate]]),MONTH(Table1[[#This Row],[OrderDate]]),1) -> 45717
A72: 45354 | B72: East | C72: Tablet | D72: =TRIM(Table1[[#This Row],[Product]]) -> Tablet | E72: =PROPER(Table1[[#This Row],[Column1]]) -> Tablet | F72: =IF(OR(E72="Chair",E72="Desk"),"Furniture",IF(OR(E72="Laptop",E72="Monitor",E72="Phone",E72="Tablet"),"Technology",IF(E72="Printer","Office Supplies","Other"))) -> Technology | G72: 15 | H72: 328.36 | I72: Store D | J72: Retail | K72: 0.15 | L72: Alice | M72: 4186.59 | N72: Gift Card | O72: WINTER15 | P72: 0 | Q72: REG100070 | R72: Cust 1907 | S72: 15.76 | T72: 45354 | U72: 45363 | V72: Eric | W72: =M72*(1-K72) -> 3558.6015 | X72: =G72*H72 -> 4925.4 | Y72: =X72-W72 -> 1366.7985 | Z72: =IF(K72=0,"No Discount",IF(K72<5%,"Low",IF(K72<15%,"Medium","High"))) -> High | AA72: =DATE(YEAR(Table1[[#This Row],[OrderDate]]),MONTH(Table1[[#This Row],[OrderDate]]),1) -> 45352
A73: 44968 | B73: Central | C73: Tablet | D73: =TRIM(Table1[[#This Row],[Product]]) -> Tablet | E73: =PROPER(Table1[[#This Row],[Column1]]) -> Tablet | F73: =IF(OR(E73="Chair",E73="Desk"),"Furniture",IF(OR(E73="Laptop",E73="Monitor",E73="Phone",E73="Tablet"),"Technology",IF(E73="Printer","Office Supplies","Other"))) -> Technology | G73: 20 | H73: 548.01 | I73: Store A | J73: Wholesale | K73: 0.1 | L73: Eva | M73: 9864.18 | N73: Credit Card | O73: WINTER15 | P73: 1 | Q73: REG100071 | R73: Cust 4639 | S73: 5.89 | T73: 44968 | U73: 44971 | V73: Cameron | W73: =M73*(1-K73) -> 8877.762 | X73: =G73*H73 -> 10960.2 | Y73: =X73-W73 -> 2082.438 | Z73: =IF(K73=0,"No Discount",IF(K73<5%,"Low",IF(K73<15%,"Medium","High"))) -> Medium | AA73: =DATE(YEAR(Table1[[#This Row],[OrderDate]]),MONTH(Table1[[#This Row],[OrderDate]]),1) -> 44958
A74: 45225 | B74: South | C74: Desk | D74: =TRIM(Table1[[#This Row],[Product]]) -> Desk | E74: =PROPER(Table1[[#This Row],[Column1]]) -> Desk | F74: =IF(OR(E74="Chair",E74="Desk"),"Furniture",IF(OR(E74="Laptop",E74="Monitor",E74="Phone",E74="Tablet"),"Technology",IF(E74="Printer","Office Supplies","Other"))) -> Furniture | G74: 13 | H74: 484.45 | I74: Store B | J74: Wholesale | K74: 0.05 | L74: Carlos | M74: 5982.9575 | N74: Gift Card | O74: WINTER15 | P74: 1 | Q74: REG100072 | R74: Cust 4153 | S74: 6.57 | T74: 45225 | U74: 45235 | V74: Sophie | W74: =M74*(1-K74) -> 5683.8096 | X74: =G74*H74 -> 6297.85 | Y74: =X74-W74 -> 614.04037 | Z74: =IF(K74=0,"No Discount",IF(K74<5%,"Low",IF(K74<15%,"Medium","High"))) -> Medium | AA74: =DATE(YEAR(Table1[[#This Row],[OrderDate]]),MONTH(Table1[[#This Row],[OrderDate]]),1) -> 45200
A75: 45220 | B75: South | C75: Monitor | D75: =TRIM(Table1[[#This Row],[Product]]) -> Monitor | E75: =PROPER(Table1[[#This Row],[Column1]]) -> Monitor | F75: =IF(OR(E75="Chair",E75="Desk"),"Furniture",IF(OR(E75="Laptop",E75="Monitor",E75="Phone",E75="Tablet"),"Technology",IF(E75="Printer","Office Supplies","Other"))) -> Technology | G75: 13 | H75: 195.84 | I75: Store A | J75: Wholesale | K75: 0.05 | L75: Alice | M75: 2418.624 | N75: Credit Card | P75: 0 | Q75: REG100073 | R75: Cust 7096 | S75: 33.52 | T75: 45220 | U75: 45227 | V75: Sophie | W75: =M75*(1-K75) -> 2297.6928 | X75: =G75*H75 -> 2545.92 | Y75: =X75-W75 -> 248.2272 | Z75: =IF(K75=0,"No Discount",IF(K75<5%,"Low",IF(K75<15%,"Medium","High"))) -> Medium | AA75: =DATE(YEAR(Table1[[#This Row],[OrderDate]]),MONTH(Table1[[#This Row],[OrderDate]]),1) -> 45200
A76: 45305 | B76: Central | C76: Tablet | D76: =TRIM(Table1[[#This Row],[Product]]) -> Tablet | E76: =PROPER(Table1[[#This Row],[Column1]]) -> Tablet | F76: =IF(OR(E76="Chair",E76="Desk"),"Furniture",IF(OR(E76="Laptop",E76="Monitor",E76="Phone",E76="Tablet"),"Technology",IF(E76="Printer","Office Supplies","Other"))) -> Technology | G76: 19 | H76: 29.94 | I76: Store D | J76: Retail | K76: 0.15 | L76: Diana | M76: 483.531 | N76: Debit Card | O76: FREESHIP | P76: 0 | Q76: REG100074 | R76: Cust 3806 | S76: 33.59 | T76: 45305 | U76: 45311 | V76: Cameron | W76: =M76*(1-K76) -> 411.00135 | X76: =G76*H76 -> 568.86 | Y76: =X76-W76 -> 157.85865 | Z76: =IF(K76=0,"No Discount",IF(K76<5%,"Low",IF(K76<15%,"Medium","High"))) -> High | AA76: =DATE(YEAR(Table1[[#This Row],[OrderDate]]),MONTH(Table1[[#This Row],[OrderDate]]),1) -> 45292
A77: 45134 | B77: Central | C77: Desk | D77: =TRIM(Table1[[#This Row],[Product]]) -> Desk | E77: =PROPER(Table1[[#This Row],[Column1]]) -> Desk | F77: =IF(OR(E77="Chair",E77="Desk"),"Furniture",IF(OR(E77="Laptop",E77="Monitor",E77="Phone",E77="Tablet"),"Technology",IF(E77="Printer","Office Supplies","Other"))) -> Furniture | G77: 10 | H77: 553.91 | I77: Store D | J77: Wholesale | K77: 0.1 | L77: Eva | M77: 4985.19 | N77: Online | P77: 0 | Q77: REG100075 | R77: Cust 9345 | S77: 31.3 | T77: 45134 | U77: 45138 | V77: Cameron | W77: =M77*(1-K77) -> 4486.671 | X77: =G77*H77 -> 5539.1 | Y77: =X77-W77 -> 1052.429 | Z77: =IF(K77=0,"No Discount",IF(K77<5%,"Low",IF(K77<15%,"Medium","High"))) -> Medium | AA77: =DATE(YEAR(Table1[[#This Row],[OrderDate]]),MONTH(Table1[[#This Row],[OrderDate]]),1) -> 45108
A78: 45588 | B78: South | C78: Phone | D78: =TRIM(Table1[[#This Row],[Product]]) -> Phone | E78: =PROPER(Table1[[#This Row],[Column1]]) -> Phone | F78: =IF(OR(E78="Chair",E78="Desk"),"Furniture",IF(OR(E78="Laptop",E78="Monitor",E78="Phone",E78="Tablet"),"Technology",IF(E78="Printer","Office Supplies","Other"))) -> Technology | G78: 14 | H78: 445.52 | I78: Store B | J78: Retail | K78: 0.1 | L78: Bob | M78: 5613.552 | N78: Online | O78: SAVE10 | P78: 0 | Q78: REG100076 | R78: Cust 4456 | S78: 14.41 | T78: 45588 | U78: 45590 | V78: Sophie | W78: =M78*(1-K78) -> 5052.1968 | X78: =G78*H78 -> 6237.28 | Y78: =X78-W78 -> 1185.0832 | Z78: =IF(K78=0,"No Discount",IF(K78<5%,"Low",IF(K78<15%,"Medium","High"))) -> Medium | AA78: =DATE(YEAR(Table1[[#This Row],[OrderDate]]),MONTH(Table1[[#This Row],[OrderDate]]),1) -> 45566
A79: 45195 | B79: South | C79: Chair | D79: =TRIM(Table1[[#This Row],[Product]]) -> Chair | E79: =PROPER(Table1[[#This Row],[Column1]]) -> Chair | F79: =IF(OR(E79="Chair",E79="Desk"),"Furniture",IF(OR(E79="Laptop",E79="Monitor",E79="Phone",E79="Tablet"),"Technology",IF(E79="Printer","Office Supplies","Other"))) -> Furniture | G79: 5 | H79: 551.58 | I79: Store B | J79: Retail | K79: 0.15 | L79: Alice | M79: 2344.215 | N79: Online | O79: WINTER15 | P79: 1 | Q79: REG100077 | R79: Cust 1089 | S79: 7.87 | T79: 45195 | U79: 45200 | V79: Sophie | W79: =M79*(1-K79) -> 1992.5828 | X79: =G79*H79 -> 2757.9 | Y79: =X79-W79 -> 765.31725 | Z79: =IF(K79=0,"No Discount",IF(K79<5%,"Low",IF(K79<15%,"Medium","High"))) -> High | AA79: =DATE(YEAR(Table1[[#This Row],[OrderDate]]),MONTH(Table1[[#This Row],[OrderDate]]),1) -> 45170
A80: 45276 | B80: East | C80: Phone | D80: =TRIM(Table1[[#This Row],[Product]]) -> Phone | E80: =PROPER(Table1[[#This Row],[Column1]]) -> Phone | F80: =IF(OR(E80="Chair",E80="Desk"),"Furniture",IF(OR(E80="Laptop",E80="Monitor",E80="Phone",E80="Tablet"),"Technology",IF(E80="Printer","Office Supplies","Other"))) -> Technology | G80: 13 | H80: 241.4 | I80: Store D | J80: Retail | K80: 0 | L80: Carlos | M80: 3138.2 | N80: Gift Card | O80: SAVE10 | P80: 0 | Q80: REG100078 | R80: Cust 7230 | S80: 49.05 | T80: 45276 | U80: 45280 | V80: Eric | W80: =M80*(1-K80) -> 3138.2 | X80: =G80*H80 -> 3138.2 | Y80: =X80-W80 -> 0 | Z80: =IF(K80=0,"No Discount",IF(K80<5%,"Low",IF(K80<15%,"Medium","High"))) -> No Discount | AA80: =DATE(YEAR(Table1[[#This Row],[OrderDate]]),MONTH(Table1[[#This Row],[OrderDate]]),1) -> 45261
A81: 45293 | B81: Central | C81: Printer | D81: =TRIM(Table1[[#This Row],[Product]]) -> Printer | E81: =PROPER(Table1[[#This Row],[Column1]]) -> Printer | F81: =IF(OR(E81="Chair",E81="Desk"),"Furniture",IF(OR(E81="Laptop",E81="Monitor",E81="Phone",E81="Tablet"),"Technology",IF(E81="Printer","Office Supplies","Other"))) -> Office Supplies | G81: 19 | H81: 351.93 | I81: Store A | J81: Wholesale | K81: 0 | L81: Alice | M81: 6686.67 | N81: Credit Card | P81: 0 | Q81: REG100079 | R81: Cust 6597 | S81: 39.98 | T81: 45293 | U81: 45296 | V81: Cameron | W81: =M81*(1-K81) -> 6686.67 | X81: =G81*H81 -> 6686.67 | Y81: =X81-W81 -> 0 | Z81: =IF(K81=0,"No Discount",IF(K81<5%,"Low",IF(K81<15%,"Medium","High"))) -> No Discount | AA81: =DATE(YEAR(Table1[[#This Row],[OrderDate]]),MONTH(Table1[[#This Row],[OrderDate]]),1) -> 45292
A82: 45338 | B82: North | C82: Phone | D82: =TRIM(Table1[[#This Row],[Product]]) -> Phone | E82: =PROPER(Table1[[#This Row],[Column1]]) -> Phone | F82: =IF(OR(E82="Chair",E82="Desk"),"Furniture",IF(OR(E82="Laptop",E82="Monitor",E82="Phone",E82="Tablet"),"Technology",IF(E82="Printer","Office Supplies","Other"))) -> Technology | G82: 4 | H82: 83.75 | I82: Store A | J82: Retail | K82: 0.05 | L82: Alice | M82: 318.25 | N82: Debit Card | O82: SAVE10 | P82: 1 | Q82: REG100080 | R82: Cust 4108 | S82: 38.82 | T82: 45338 | U82: 45347 | V82: Ryan | W82: =M82*(1-K82) -> 302.3375 | X82: =G82*H82 -> 335 | Y82: =X82-W82 -> 32.6625 | Z82: =IF(K82=0,"No Discount",IF(K82<5%,"Low",IF(K82<15%,"Medium","High"))) -> Medium | AA82: =DATE(YEAR(Table1[[#This Row],[OrderDate]]),MONTH(Table1[[#This Row],[OrderDate]]),1) -> 45323
A83: 45415 | B83: East | C83: Monitor | D83: =TRIM(Table1[[#This Row],[Product]]) -> Monitor | E83: =PROPER(Table1[[#This Row],[Column1]]) -> Monitor | F83: =IF(OR(E83="Chair",E83="Desk"),"Furniture",IF(OR(E83="Laptop",E83="Monitor",E83="Phone",E83="Tablet"),"Technology",IF(E83="Printer","Office Supplies","Other"))) -> Technology | G83: 5 | H83: 416.95 | I83: Store A | J83: Wholesale | K83: 0.15 | L83: Frank | M83: 1772.0375 | N83: Online | P83: 1 | Q83: REG100081 | R83: Cust 2883 | S83: 24.03 | T83: 45415 | U83: 45424 | V83: Eric | W83: =M83*(1-K83) -> 1506.2319 | X83: =G83*H83 -> 2084.75 | Y83: =X83-W83 -> 578.51813 | Z83: =IF(K83=0,"No Discount",IF(K83<5%,"Low",IF(K83<15%,"Medium","High"))) -> High | AA83: =DATE(YEAR(Table1[[#This Row],[OrderDate]]),MONTH(Table1[[#This Row],[OrderDate]]),1) -> 45413
A84: 45073 | B84: West | C84: Monitor | D84: =TRIM(Table1[[#This Row],[Product]]) -> Monitor | E84: =PROPER(Table1[[#This Row],[Column1]]) -> Monitor | F84: =IF(OR(E84="Chair",E84="Desk"),"Furniture",IF(OR(E84="Laptop",E84="Monitor",E84="Phone",E84="Tablet"),"Technology",IF(E84="Printer","Office Supplies","Other"))) -> Technology | G84: 18 | H84: 142.43 | I84: Store C | J84: Retail | K84: 0.05 | L84: Bob | M84: 2435.553 | N84: Credit Card | O84: SAVE10 | P84: 1 | Q84: REG100082 | R84: Cust 5018 | S84: 12.38 | T84: 45073 | U84: 45079 | V84: Wendy | W84: =M84*(1-K84) -> 2313.7753 | X84: =G84*H84 -> 2563.74 | Y84: =X84-W84 -> 249.96465 | Z84: =IF(K84=0,"No Discount",IF(K84<5%,"Low",IF(K84<15%,"Medium","High"))) -> Medium | AA84: =DATE(YEAR(Table1[[#This Row],[OrderDate]]),MONTH(Table1[[#This Row],[OrderDate]]),1) -> 45047
A85: 44931 | B85: East | C85: Desk | D85: =TRIM(Table1[[#This Row],[Product]]) -> Desk | E85: =PROPER(Table1[[#This Row],[Column1]]) -> Desk | F85: =IF(OR(E85="Chair",E85="Desk"),"Furniture",IF(OR(E85="Laptop",E85="Monitor",E85="Phone",E85="Tablet"),"Technology",IF(E85="Printer","Office Supplies","Other"))) -> Furniture | G85: 12 | H85: 582.52 | I85: Store A | J85: Wholesale | K85: 0 | L85: Bob | M85: 6990.24 | N85: Credit Card | O85: FREESHIP | P85: 0 | Q85: REG100083 | R85: Cust 1231 | S85: 41.16 | T85: 44931 | U85: 44937 | V85: Eric | W85: =M85*(1-K85) -> 6990.24 | X85: =G85*H85 -> 6990.24 | Y85: =X85-W85 -> 0 | Z85: =IF(K85=0,"No Discount",IF(K85<5%,"Low",IF(K85<15%,"Medium","High"))) -> No Discount | AA85: =DATE(YEAR(Table1[[#This Row],[OrderDate]]),MONTH(Table1[[#This Row],[OrderDate]]),1) -> 44927
A86: 45798 | B86: East | C86: Chair | D86: =TRIM(Table1[[#This Row],[Product]]) -> Chair | E86: =PROPER(Table1[[#This Row],[Column1]]) -> Chair | F86: =IF(OR(E86="Chair",E86="Desk"),"Furniture",IF(OR(E86="Laptop",E86="Monitor",E86="Phone",E86="Tablet"),"Technology",IF(E86="Printer","Office Supplies","Other"))) -> Furniture | G86: 20 | H86: 129.56 | I86: Store A | J86: Retail | K86: 0.15 | L86: Diana | M86: 2202.52 | N86: Online | O86: WINTER15 | P86: 0 | Q86: REG100084 | R86: Cust 2209 | S86: 40.21 | T86: 45798 | U86: 45800 | V86: Eric | W86: =M86*(1-K86) -> 1872.142 | X86: =G86*H86 -> 2591.2 | Y86: =X86-W86 -> 719.058 | Z86: =IF(K86=0,"No Discount",IF(K86<5%,"Low",IF(K86<15%,"Medium","High"))) -> High | AA86: =DATE(YEAR(Table1[[#This Row],[OrderDate]]),MONTH(Table1[[#This Row],[OrderDate]]),1) -> 45778
A87: 45128 | B87: Central | C87: Tablet | D87: =TRIM(Table1[[#This Row],[Product]]) -> Tablet | E87: =PROPER(Table1[[#This Row],[Column1]]) -> Tablet | F87: =IF(OR(E87="Chair",E87="Desk"),"Furniture",IF(OR(E87="Laptop",E87="Monitor",E87="Phone",E87="Tablet"),"Technology",IF(E87="Printer","Office Supplies","Other"))) -> Technology | G87: 17 | H87: 431.82 | I87: Store B | J87: Retail | K87: 0 | L87: Eva | M87: 7340.94 | N87: Gift Card | O87: FREESHIP | P87: 1 | Q87: REG100085 | R87: Cust 6684 | S87: 37.75 | T87: 45128 | U87: 45132 | V87: Cameron | W87: =M87*(1-K87) -> 7340.94 | X87: =G87*H87 -> 7340.94 | Y87: =X87-W87 -> 0 | Z87: =IF(K87=0,"No Discount",IF(K87<5%,"Low",IF(K87<15%,"Medium","High"))) -> No Discount | AA87: =DATE(YEAR(Table1[[#This Row],[OrderDate]]),MONTH(Table1[[#This Row],[OrderDate]]),1) -> 45108
A88: 45802 | B88: East | C88: Laptop | D88: =TRIM(Table1[[#This Row],[Product]]) -> Laptop | E88: =PROPER(Table1[[#This Row],[Column1]]) -> Laptop | F88: =IF(OR(E88="Chair",E88="Desk"),"Furniture",IF(OR(E88="Laptop",E88="Monitor",E88="Phone",E88="Tablet"),"Technology",IF(E88="Printer","Office Supplies","Other"))) -> Technology | G88: 15 | H88: 15.85 | I88: Store C | J88: Retail | K88: 0 | L88: Bob | M88: 237.75 | N88: Debit Card | O88: WINTER15 | P88: 0 | Q88: REG100086 | R88: Cust 5289 | S88: 23.49 | T88: 45802 | U88: 45811 | V88: Eric | W88: =M88*(1-K88) -> 237.75 | X88: =G88*H88 -> 237.75 | Y88: =X88-W88 -> 0 | Z88: =IF(K88=0,"No Discount",IF(K88<5%,"Low",IF(K88<15%,"Medium","High"))) -> No Discount | AA88: =DATE(YEAR(Table1[[#This Row],[OrderDate]]),MONTH(Table1[[#This Row],[OrderDate]]),1) -> 45778
A89: 45612 | B89: South | C89: Tablet | D89: =TRIM(Table1[[#This Row],[Product]]) -> Tablet | E89: =PROPER(Table1[[#This Row],[Column1]]) -> Tablet | F89: =IF(OR(E89="Chair",E89="Desk"),"Furniture",IF(OR(E89="Laptop",E89="Monitor",E89="Phone",E89="Tablet"),"Technology",IF(E89="Printer","Office Supplies","Other"))) -> Technology | G89: 20 | H89: 548.34 | I89: Store B | J89: Retail | K89: 0.1 | L89: Bob | M89: 9870.12 | N89: Gift Card | O89: WINTER15 | P89: 0 | Q89: REG100087 | R89: Cust 9159 | S89: 33.47 | T89: 45612 | U89: 45618 | V89: Sophie | W89: =M89*(1-K89) -> 8883.108 | X89: =G89*H89 -> 10966.8 | Y89: =X89-W89 -> 2083.692 | Z89: =IF(K89=0,"No Discount",IF(K89<5%,"Low",IF(K89<15%,"Medium","High"))) -> Medium | AA89: =DATE(YEAR(Table1[[#This Row],[OrderDate]]),MONTH(Table1[[#This Row],[OrderDate]]),1) -> 45597
A90: 45249 | B90: North | C90: Laptop | D90: =TRIM(Table1[[#This Row],[Product]]) -> Laptop | E90: =PROPER(Table1[[#This Row],[Column1]]) -> Laptop | F90: =IF(OR(E90="Chair",E90="Desk"),"Furniture",IF(OR(E90="Laptop",E90="Monitor",E90="Phone",E90="Tablet"),"Technology",IF(E90="Printer","Office Supplies","Other"))) -> Technology | G90: 16 | H90: 525.83 | I90: Store C | J90: Wholesale | K90: 0.05 | L90: Frank | M90: 7992.616 | N90: Online | P90: 0 | Q90: REG100088 | R90: Cust 4844 | S90: 36.47 | T90: 45249 | U90: 45255 | V90: Ryan | W90: =M90*(1-K90) -> 7592.9852 | X90: =G90*H90 -> 8413.28 | Y90: =X90-W90 -> 820.2948 | Z90: =IF(K90=0,"No Discount",IF(K90<5%,"Low",IF(K90<15%,"Medium","High"))) -> Medium | AA90: =DATE(YEAR(Table1[[#This Row],[OrderDate]]),MONTH(Table1[[#This Row],[OrderDate]]),1) -> 45231
A91: 45669 | B91: Central | C91: Laptop | D91: =TRIM(Table1[[#This Row],[Product]]) -> Laptop | E91: =PROPER(Table1[[#This Row],[Column1]]) -> Laptop | F91: =IF(OR(E91="Chair",E91="Desk"),"Furniture",IF(OR(E91="Laptop",E91="Monitor",E91="Phone",E91="Tablet"),"Technology",IF(E91="Printer","Office Supplies","Other"))) -> Technology | G91: 15 | H91: 411.38 | I91: Store A | J91: Wholesale | K91: 0.05 | L91: Bob | M91: 5862.165 | N91: Online | O91: SAVE10 | P91: 0 | Q91: REG100089 | R91: Cust 3273 | S91: 48.51 | T91: 45669 | U91: 45678 | V91: Cameron | W91: =M91*(1-K91) -> 5569.0567 | X91: =G91*H91 -> 6170.7 | Y91: =X91-W91 -> 601.64325 | Z91: =IF(K91=0,"No Discount",IF(K91<5%,"Low",IF(K91<15%,"Medium","High"))) -> Medium | AA91: =DATE(YEAR(Table1[[#This Row],[OrderDate]]),MONTH(Table1[[#This Row],[OrderDate]]),1) -> 45658
A92: 45014 | B92: North | C92: Monitor | D92: =TRIM(Table1[[#This Row],[Product]]) -> Monitor | E92: =PROPER(Table1[[#This Row],[Column1]]) -> Monitor | F92: =IF(OR(E92="Chair",E92="Desk"),"Furniture",IF(OR(E92="Laptop",E92="Monitor",E92="Phone",E92="Tablet"),"Technology",IF(E92="Printer","Office Supplies","Other"))) -> Technology | G92: 19 | H92: 559.95 | I92: Store A | J92: Wholesale | K92: 0.1 | L92: Carlos | M92: 9575.145 | N92: Credit Card | O92: WINTER15 | P92: 0 | Q92: REG100090 | R92: Cust 8160 | S92: 18.3 | T92: 45014 | U92: 45019 | V92: Ryan | W92: =M92*(1-K92) -> 8617.6305 | X92: =G92*H92 -> 10639.05 | Y92: =X92-W92 -> 2021.4195 | Z92: =IF(K92=0,"No Discount",IF(K92<5%,"Low",IF(K92<15%,"Medium","High"))) -> Medium | AA92: =DATE(YEAR(Table1[[#This Row],[OrderDate]]),MONTH(Table1[[#This Row],[OrderDate]]),1) -> 44986
A93: 45717 | B93: North | C93: Desk | D93: =TRIM(Table1[[#This Row],[Product]]) -> Desk | E93: =PROPER(Table1[[#This Row],[Column1]]) -> Desk | F93: =IF(OR(E93="Chair",E93="Desk"),"Furniture",IF(OR(E93="Laptop",E93="Monitor",E93="Phone",E93="Tablet"),"Technology",IF(E93="Printer","Office Supplies","Other"))) -> Furniture | G93: 8 | H93: 179.9 | I93: Store C | J93: Retail | K93: 0.05 | L93: Carlos | M93: 1367.24 | N93: Online | O93: SAVE10 | P93: 0 | Q93: REG100091 | R93: Cust 4439 | S93: 14.8 | T93: 45717 | U93: 45721 | V93: Ryan | W93: =M93*(1-K93) -> 1298.878 | X93: =G93*H93 -> 1439.2 | Y93: =X93-W93 -> 140.322 | Z93: =IF(K93=0,"No Discount",IF(K93<5%,"Low",IF(K93<15%,"Medium","High"))) -> Medium | AA93: =DATE(YEAR(Table1[[#This Row],[OrderDate]]),MONTH(Table1[[#This Row],[OrderDate]]),1) -> 45717
A94: 45217 | B94: North | C94: Chair | D94: =TRIM(Table1[[#This Row],[Product]]) -> Chair | E94: =PROPER(Table1[[#This Row],[Column1]]) -> Chair | F94: =IF(OR(E94="Chair",E94="Desk"),"Furniture",IF(OR(E94="Laptop",E94="Monitor",E94="Phone",E94="Tablet"),"Technology",IF(E94="Printer","Office Supplies","Other"))) -> Furniture | G94: 12 | H94: 494.15 | I94: Store B | J94: Wholesale | K94: 0.15 | L94: Diana | M94: 5040.33 | N94: Online | O94: SAVE10 | P94: 1 | Q94: REG100092 | R94: Cust 1127 | S94: 18.05 | T94: 45217 | U94: 45219 | V94: Ryan | W94: =M94*(1-K94) -> 4284.2805 | X94: =G94*H94 -> 5929.8 | Y94: =X94-W94 -> 1645.5195 | Z94: =IF(K94=0,"No Discount",IF(K94<5%,"Low",IF(K94<15%,"Medium","High"))) -> High | AA94: =DATE(YEAR(Table1[[#This Row],[OrderDate]]),MONTH(Table1[[#This Row],[OrderDate]]),1) -> 45200
A95: 45760 | B95: East | C95: Desk | D95: =TRIM(Table1[[#This Row],[Product]]) -> Desk | E95: =PROPER(Table1[[#This Row],[Column1]]) -> Desk | F95: =IF(OR(E95="Chair",E95="Desk"),"Furniture",IF(OR(E95="Laptop",E95="Monitor",E95="Phone",E95="Tablet"),"Technology",IF(E95="Printer","Office Supplies","Other"))) -> Furniture | G95: 10 | H95: 462.99 | I95: Store C | J95: Wholesale | K95: 0 | L95: Bob | M95: 4629.9 | N95: Credit Card | O95: WINTER15 | P95: 0 | Q95: REG100093 | R95: Cust 4696 | S95: 5.01 | T95: 45760 | U95: 45762 | V95: Eric | W95: =M95*(1-K95) -> 4629.9 | X95: =G95*H95 -> 4629.9 | Y95: =X95-W95 -> 0 | Z95: =IF(K95=0,"No Discount",IF(K95<5%,"Low",IF(K95<15%,"Medium","High"))) -> No Discount | AA95: =DATE(YEAR(Table1[[#This Row],[OrderDate]]),MONTH(Table1[[#This Row],[OrderDate]]),1) -> 45748
A96: 45790 | B96: Central | C96: Laptop | D96: =TRIM(Table1[[#This Row],[Product]]) -> Laptop | E96: =PROPER(Table1[[#This Row],[Column1]]) -> Laptop | F96: =IF(OR(E96="Chair",E96="Desk"),"Furniture",IF(OR(E96="Laptop",E96="Monitor",E96="Phone",E96="Tablet"),"Technology",IF(E96="Printer","Office Supplies","Other"))) -> Technology | G96: 7 | H96: 460.24 | I96: Store A | J96: Retail | K96: 0.05 | L96: Alice | M96: 3060.596 | N96: Cash | O96: SAVE10 | P96: 1 | Q96: REG100094 | R96: Cust 3014 | S96: 11.54 | T96: 45790 | U96: 45800 | V96: Cameron | W96: =M96*(1-K96) -> 2907.5662 | X96: =G96*H96 -> 3221.68 | Y96: =X96-W96 -> 314.1138 | Z96: =IF(K96=0,"No Discount",IF(K96<5%,"Low",IF(K96<15%,"Medium","High"))) -> Medium | AA96: =DATE(YEAR(Table1[[#This Row],[OrderDate]]),MONTH(Table1[[#This Row],[OrderDate]]),1) -> 45778
A97: 45403 | B97: West | C97: Printer | D97: =TRIM(Table1[[#This Row],[Product]]) -> Printer | E97: =PROPER(Table1[[#This Row],[Column1]]) -> Printer | F97: =IF(OR(E97="Chair",E97="Desk"),"Furniture",IF(OR(E97="Laptop",E97="Monitor",E97="Phone",E97="Tablet"),"Technology",IF(E97="Printer","Office Supplies","Other"))) -> Office Supplies | G97: 17 | H97: 309.52 | I97: Store B | J97: Wholesale | K97: 0.05 | L97: Eva | M97: 4998.748 | N97: Online | O97: FREESHIP | P97: 0 | Q97: REG100095 | R97: Cust 2539 | S97: 6.11 | T97: 45403 | U97: 45409 | V97: Wendy | W97: =M97*(1-K97) -> 4748.8106 | X97: =G97*H97 -> 5261.84 | Y97: =X97-W97 -> 513.0294 | Z97: =IF(K97=0,"No Discount",IF(K97<5%,"Low",IF(K97<15%,"Medium","High"))) -> Medium | AA97: =DATE(YEAR(Table1[[#This Row],[OrderDate]]),MONTH(Table1[[#This Row],[OrderDate]]),1) -> 45383
A98: 45688 | B98: Central | C98: Monitor | D98: =TRIM(Table1[[#This Row],[Product]]) -> Monitor | E98: =PROPER(Table1[[#This Row],[Column1]]) -> Monitor | F98: =IF(OR(E98="Chair",E98="Desk"),"Furniture",IF(OR(E98="Laptop",E98="Monitor",E98="Phone",E98="Tablet"),"Technology",IF(E98="Printer","Office Supplies","Other"))) -> Technology | G98: 1 | H98: 323.83 | I98: Store B | J98: Wholesale | K98: 0.05 | L98: Eva | M98: 307.6385 | N98: Credit Card | O98: WINTER15 | P98: 0 | Q98: REG100096 | R98: Cust 3916 | S98: 27.48 | T98: 45688 | U98: 45696 | V98: Cameron | W98: =M98*(1-K98) -> 292.25657 | X98: =G98*H98 -> 323.83 | Y98: =X98-W98 -> 31.573425 | Z98: =IF(K98=0,"No Discount",IF(K98<5%,"Low",IF(K98<15%,"Medium","High"))) -> Medium | AA98: =DATE(YEAR(Table1[[#This Row],[OrderDate]]),MONTH(Table1[[#This Row],[OrderDate]]),1) -> 45658
A99: 45730 | B99: Central | C99: Chair | D99: =TRIM(Table1[[#This Row],[Product]]) -> Chair | E99: =PROPER(Table1[[#This Row],[Column1]]) -> Chair | F99: =IF(OR(E99="Chair",E99="Desk"),"Furniture",IF(OR(E99="Laptop",E99="Monitor",E99="Phone",E99="Tablet"),"Technology",IF(E99="Printer","Office Supplies","Other"))) -> Furniture | G99: 10 | H99: 503.07 | I99: Store C | J99: Retail | K99: 0 | L99: Bob | M99: 5030.7 | N99: Credit Card | O99: FREESHIP | P99: 0 | Q99: REG100097 | R99: Cust 6329 | S99: 44.61 | T99: 45730 | U99: 45735 | V99: Cameron | W99: =M99*(1-K99) -> 5030.7 | X99: =G99*H99 -> 5030.7 | Y99: =X99-W99 -> 0 | Z99: =IF(K99=0,"No Discount",IF(K99<5%,"Low",IF(K99<15%,"Medium","High"))) -> No Discount | AA99: =DATE(YEAR(Table1[[#This Row],[OrderDate]]),MONTH(Table1[[#This Row],[OrderDate]]),1) -> 45717
A100: 45438 | B100: West | C100: Laptop | D100: =TRIM(Table1[[#This Row],[Product]]) -> Laptop | E100: =PROPER(Table1[[#This Row],[Column1]]) -> Laptop | F100: =IF(OR(E100="Chair",E100="Desk"),"Furniture",IF(OR(E100="Laptop",E100="Monitor",E100="Phone",E100="Tablet"),"Technology",IF(E100="Printer","Office Supplies","Other"))) -> Technology | G100: 20 | H100: 491.68 | I100: Store D | J100: Wholesale | K100: 0.15 | L100: Alice | M100: 8358.56 | N100: Online | O100: SAVE10 | P100: 1 | Q100: REG100098 | R100: Cust 4384 | S100: 43.46 | T100: 45438 | U100: 45441 | V100: Wendy | W100: =M100*(1-K100) -> 7104.776 | X100: =G100*H100 -> 9833.6 | Y100: =X100-W100 -> 2728.824 | Z100: =IF(K100=0,"No Discount",IF(K100<5%,"Low",IF(K100<15%,"Medium","High"))) -> High | AA100: =DATE(YEAR(Table1[[#This Row],[OrderDate]]),MONTH(Table1[[#This Row],[OrderDate]]),1) -> 45413
...

Sheet Pivot Data
A3: Total Sales | B3: Total Profit | C3: Total Orders | F3: Region | G3: Sum of Net Sales | H3: Sum of Profit | J3: Discount Category | K3: Sum of Profit
A4: 4072350.1 | B4: 655542.86 | C4: 1500 | D4: =GETPIVOTDATA("Total Profit",$A$3)/GETPIVOTDATA("Total Sales",$A$3) -> 0.16097409 | F4: Central | G4: 787211.78 | H4: 127575.2 | J4: No Discount | K4: 0
F5: East | G5: 827104.35 | H5: 120259.06 | J5: High | K5: 312142.17
F6: North | G6: 894607.17 | H6: 156474.61 | J6: Medium | K6: 343400.69
F7: South | G7: 770077.07 | H7: 123051.8 | J7: Grand Total | K7: 655542.86
A8: Years (Year-Month) | B8: Months (Year-Month) | C8: Sum of Net Sales | F8: West | G8: 793349.71 | H8: 128182.19
A9: 2023 | B9: Jan | C9: 145345.99 | F9: Grand Total | G9: 4072350.1 | H9: 655542.86 | J9: Salesperson | K9: Sum of Net Sales
B10: Feb | C10: 131509.56 | J10: Diana | K10: 626990.02
B11: Mar | C11: 188371.35 | J11: Eva | K11: 647454.24
B12: Apr | C12: 139489.97 | F12: Category | G12: Sum of Net Sales | J12: Carlos | K12: 654539.6
B13: May | C13: 108538.29 | F13: Furniture | G13: 1095216.7 | J13: Frank | K13: 663561.71
B14: Jun | C14: 126092.11 | F14: Office Supplies | G14: 632393.83 | J14: Alice | K14: 736279.13
B15: Jul | C15: 131292.93 | F15: Technology | G15: 2344739.6 | J15: Bob | K15: 743525.39
B16: Aug | C16: 149487.16 | F16: Grand Total | G16: 4072350.1 | J16: Grand Total | K16: 4072350.1
B17: Sep | C17: 141740.3
B18: Oct | C18: 72787.612
B19: Nov | C19: 134433.09
B20: Dec | C20: 111205.08 | F20: Product | G20: Sum of Profit
A21: 2023 Total | C21: 1580293.4 | F21: Phone | G21: 74306.793
A22: 2024 | B22: Jan | C22: 161397.95 | F22: Chair | G22: 87964.503
B23: Feb | C23: 126356.26 | F23: Desk | G23: 88243.92
B24: Mar | C24: 131192.8 | F24: Tablet | G24: 96417.503
B25: Apr | C25: 153705.86 | F25: Monitor | G25: 98011.144
B26: May | C26: 123703.11 | F26: Laptop | G26: 99487.012
B27: Jun | C27: 150316.26 | F27: Printer | G27: 111111.98
B28: Jul | C28: 129300.51 | F28: Grand Total | G28: 655542.86
B29: Aug | C29: 120083.84
B30: Sep | C30: 121676.03
B31: Oct | C31: 165124.53
B32: Nov | C32: 130480.49
B33: Dec | C33: 134562.41
A34: 2024 Total | C34: 1647900
A35: 2025 | B35: Jan | C35: 161275.03
B36: Feb | C36: 125728.24
B37: Mar | C37: 170017.68
B38: Apr | C38: 120345.08
B39: May | C39: 139774.58
B40: Jun | C40: 127015.99
A41: 2025 Total | C41: 844156.6
A42: Grand Total | C42: 4072350.1
